Workbook

Sheet Account_Setup_and_Data_Load
A1: Organization Link | B1: Organization | C1: Location | D1: Location Ref | E1: Account Style Link | F1: Account Style Caption | G1: Account Subtype | H1: Account Number | I1: Account Reference | J1: Account Supplier | K1: Account Reader | L1: Record Start YYYY-MM-DD | M1: Record End YYYY-MM-DD | N1: Record Data Quality | O1: Record Billing Type | P1: Record Subtype | Q1: Record Entry Method | R1: Record Reference | S1: Record Invoice Number | T1: Quantity | U1: Total Cost
A2: 37395 | B2: Downer | C2: REV_Transport & Infrastructure NZ | D2: L9.DNZJ.8134 | E2: 7868 | F2: Revenue - AUD Million | H2: FY26REV_Transport & Infrastructure NZ | I2: FY26REV_Transport & Infrastructure NZ | J2: Downer | K2: Revenue | L2: 45839 | M2: 45869 | N2: Actual | O2: Standard | Q2: Insert | R2: T&I NZ North | S2: T&I NZ North | T2: 30.3
A3: 37395 | B3: Downer | C3: REV_Transport & Infrastructure NZ | D3: L9.DNZJ.8134 | E3: 7868 | F3: Revenue - AUD Million | H3: FY26REV_Transport & Infrastructure NZ | I3: FY26REV_Transport & Infrastructure NZ | J3: Downer | K3: Revenue | L3: 45839 | M3: 45869 | N3: Actual | O3: Standard | Q3: Insert | R3: T&I NZ South | S3: T&I NZ South | T3: 27.8
A4: 37395 | B4: Downer | C4: REV_Transport & Infrastructure NZ | D4: L9.DNZJ.8134 | E4: 7868 | F4: Revenue - AUD Million | H4: FY26REV_Transport & Infrastructure NZ | I4: FY26REV_Transport & Infrastructure NZ | J4: Downer | K4: Revenue | L4: 45839 | M4: 45869 | N4: Actual | O4: Standard | Q4: Insert | R4: T&I NZ Infrastructure Delivery | S4: T&I NZ Infrastructure Delivery | T4: 24.6
A5: 37395 | B5: Downer | C5: REV_Transport & Infrastructure NZ | D5: L9.DNZJ.8134 | E5: 7868 | F5: Revenue - AUD Million | H5: FY26REV_Transport & Infrastructure NZ | I5: FY26REV_Transport & Infrastructure NZ | J5: Downer | K5: Revenue | L5: 45839 | M5: 45869 | N5: Actual | O5: Standard | Q5: Insert | R5: T&I NZ Hawkins | S5: T&I NZ Hawkins | T5: 41.4
A6: 37395 | B6: Downer | C6: REV_Transport & Infrastructure NZ | D6: L9.DNZJ.8134 | E6: 7868 | F6: Revenue - AUD Million | H6: FY26REV_Transport & Infrastructure NZ | I6: FY26REV_Transport & Infrastructure NZ | J6: Downer | K6: Revenue | L6: 45839 | M6: 45869 | N6: Actual | O6: Standard | Q6: Insert | R6: T&I NZ National Operations | S6: T&I NZ National Operations | T6: 8.8
A7: 37395 | B7: Downer | C7: REV_Transport & Infrastructure NZ | D7: L9.DNZJ.8134 | E7: 7868 | F7: Revenue - AUD Million | H7: FY26REV_Transport & Infrastructure NZ | I7: FY26REV_Transport & Infrastructure NZ | J7: Downer | K7: Revenue | L7: 45839 | M7: 45869 | N7: Actual | O7: Standard | Q7: Insert | R7: T&I NZ Overheads | S7: T&I NZ Overheads | T7: 0
A8: 37395 | B8: Downer | C8: REV_Transport & Infrastructure NZ | D8: L9.DNZJ.8134 | E8: 7868 | F8: Revenue - AUD Million | H8: FY26REV_Transport & Infrastructure NZ | I8: FY26REV_Transport & Infrastructure NZ | J8: Downer | K8: Revenue | L8: 45839 | M8: 45869 | N8: Actual | O8: Standard | Q8: Insert | R8: T&I AU Asphalt & Products | S8: T&I AU Asphalt & Products | T8: 50.2
A9: 37395 | B9: Downer | C9: REV_Transport & Infrastructure AU | D9: L9.J.170615 | E9: 7868 | F9: Revenue - AUD Million | H9: FY26REV_Transport & Infrastructure AU | I9: FY26REV_Transport & Infrastructure AU | J9: Downer | K9: Revenue | L9: 45839 | M9: 45869 | N9: Actual | O9: Standard | Q9: Insert | R9: Maintenance & ITS | S9: Maintenance & ITS | T9: 26.2
A10: 37395 | B10: Downer | C10: REV_Transport & Infrastructure AU | D10: L9.J.170615 | E10: 7868 | F10: Revenue - AUD Million | H10: FY26REV_Transport & Infrastructure AU | I10: FY26REV_Transport & Infrastructure AU | J10: Downer | K10: Revenue | L10: 45839 | M10: 45869 | N10: Actual | O10: Standard | Q10: Insert | R10: Pavement Rehabilitation & Civils | S10: Pavement Rehabilitation & Civils | T10: 0.7
A11: 37395 | B11: Downer | C11: REV_Transport & Infrastructure AU | D11: L9.J.170615 | E11: 7868 | F11: Revenue - AUD Million | H11: FY26REV_Transport & Infrastructure AU | I11: FY26REV_Transport & Infrastructure AU | J11: Downer | K11: Revenue | L11: 45839 | M11: 45869 | N11: Actual | O11: Standard | Q11: Insert | R11: Specialised Pavements & Projects | S11: Specialised Pavements & Projects | T11: 6.8
A12: 37395 | B12: Downer | C12: REV_Transport & Infrastructure AU | D12: L9.J.170615 | E12: 7868 | F12: Revenue - AUD Million | H12: FY26REV_Transport & Infrastructure AU | I12: FY26REV_Transport & Infrastructure AU | J12: Downer | K12: Revenue | L12: 45839 | M12: 45869 | N12: Actual | O12: Standard | Q12: Insert | R12: Thin Surfacing | S12: Thin Surfacing | T12: 18.5
A13: 37395 | B13: Downer | C13: REV_Transport & Infrastructure AU | D13: L9.J.170615 | E13: 7868 | F13: Revenue - AUD Million | H13: FY26REV_Transport & Infrastructure AU | I13: FY26REV_Transport & Infrastructure AU | J13: Downer | K13: Revenue | L13: 45839 | M13: 45869 | N13: Actual | O13: Standard | Q13: Insert | R13: BIA | S13: BIA | T13: 4
... A791: 37395 | B791: Downer | C791: REV_Intra Elim | D791: CORIE | E791: 7868 | F791: Revenue - AUD Million | H791: FY26REV_Intra Elim | I791: FY26REV_Intra Elim | J791: Downer | K791: Revenue | L791: 46113 | M791: 46142 | N791: Actual | O791: Standard | Q791: Insert | R791: Intra Elim | S791: Intra Elim | T791: -0.1

Sheet Prep - with formulas
A1: Organization Link | B1: Organization | C1: Location | D1: Location Ref | E1: Account Style Link | F1: Account Style Caption | G1: Account Subtype | H1: Account Number | I1: Account Reference | J1: Account Supplier | K1: Account Reader | L1: Record Start YYYY-MM-DD | M1: Record End YYYY-MM-DD | N1: Record Data Quality | O1: Record Billing Type | P1: Record Subtype | Q1: Record Entry Method | R1: Record Reference | S1: Record Invoice Number | T1: Quantity
A2: 37395 | B2: Downer | C2: ='FY26 Revenue'!N2 -> REV_Transport & Infrastructure NZ | D2: =_xlfn.XLOOKUP(C2,'Extract_for_Locations 1 Oct 25'!B:B,'Extract_for_Locations 1 Oct 25'!E:E) -> L9.DNZJ.8134 | E2: 7868 | F2: Revenue - AUD Million | H2: =CONCATENATE("FY26REV_",'FY26 Revenue'!B2) -> FY26REV_Transport & Infrastructure NZ | I2: =CONCATENATE("FY26REV_",'FY26 Revenue'!B2) -> FY26REV_Transport & Infrastructure NZ | J2: Downer | K2: Revenue | L2: 46113 | M2: 46142 | N2: Actual | O2: Standard | Q2: Insert | R2: ='FY26 Revenue'!C2 -> T&I NZ North | S2: ='FY26 Revenue'!C2 -> T&I NZ North | T2: ='FY26 Revenue'!M2 -> 44.2
A3: 37395 | B3: Downer | C3: ='FY26 Revenue'!N3 -> REV_Transport & Infrastructure NZ | D3: =_xlfn.XLOOKUP(C3,'Extract_for_Locations 1 Oct 25'!B:B,'Extract_for_Locations 1 Oct 25'!E:E) -> L9.DNZJ.8134 | E3: 7868 | F3: Revenue - AUD Million | H3: =CONCATENATE("FY26REV_",'FY26 Revenue'!B3) -> FY26REV_Transport & Infrastructure NZ | I3: =CONCATENATE("FY26REV_",'FY26 Revenue'!B3) -> FY26REV_Transport & Infrastructure NZ | J3: Downer | K3: Revenue | L3: 46113 | M3: 46142 | N3: Actual | O3: Standard | Q3: Insert | R3: ='FY26 Revenue'!C3 -> T&I NZ South | S3: ='FY26 Revenue'!C3 -> T&I NZ South | T3: ='FY26 Revenue'!M3 -> 42.8
A4: 37395 | B4: Downer | C4: ='FY26 Revenue'!N4 -> REV_Transport & Infrastructure NZ | D4: =_xlfn.XLOOKUP(C4,'Extract_for_Locations 1 Oct 25'!B:B,'Extract_for_Locations 1 Oct 25'!E:E) -> L9.DNZJ.8134 | E4: 7868 | F4: Revenue - AUD Million | H4: =CONCATENATE("FY26REV_",'FY26 Revenue'!B4) -> FY26REV_Transport & Infrastructure NZ | I4: =CONCATENATE("FY26REV_",'FY26 Revenue'!B4) -> FY26REV_Transport & Infrastructure NZ | J4: Downer | K4: Revenue | L4: 46113 | M4: 46142 | N4: Actual | O4: Standard | Q4: Insert | R4: ='FY26 Revenue'!C4 -> T&I NZ Infrastructure Delivery | S4: ='FY26 Revenue'!C4 -> T&I NZ Infrastructure Delivery | T4: ='FY26 Revenue'!M4 -> 33.5
A5: 37395 | B5: Downer | C5: ='FY26 Revenue'!N5 -> REV_Transport & Infrastructure NZ | D5: =_xlfn.XLOOKUP(C5,'Extract_for_Locations 1 Oct 25'!B:B,'Extract_for_Locations 1 Oct 25'!E:E) -> L9.DNZJ.8134 | E5: 7868 | F5: Revenue - AUD Million | H5: =CONCATENATE("FY26REV_",'FY26 Revenue'!B5) -> FY26REV_Transport & Infrastructure NZ | I5: =CONCATENATE("FY26REV_",'FY26 Revenue'!B5) -> FY26REV_Transport & Infrastructure NZ | J5: Downer | K5: Revenue | L5: 46113 | M5: 46142 | N5: Actual | O5: Standard | Q5: Insert | R5: ='FY26 Revenue'!C5 -> T&I NZ Hawkins | S5: ='FY26 Revenue'!C5 -> T&I NZ Hawkins | T5: ='FY26 Revenue'!M5 -> 51
A6: 37395 | B6: Downer | C6: ='FY26 Revenue'!N6 -> REV_Transport & Infrastructure NZ | D6: =_xlfn.XLOOKUP(C6,'Extract_for_Locations 1 Oct 25'!B:B,'Extract_for_Locations 1 Oct 25'!E:E) -> L9.DNZJ.8134 | E6: 7868 | F6: Revenue - AUD Million | H6: =CONCATENATE("FY26REV_",'FY26 Revenue'!B6) -> FY26REV_Transport & Infrastructure NZ | I6: =CONCATENATE("FY26REV_",'FY26 Revenue'!B6) -> FY26REV_Transport & Infrastructure NZ | J6: Downer | K6: Revenue | L6: 46113 | M6: 46142 | N6: Actual | O6: Standard | Q6: Insert | R6: ='FY26 Revenue'!C6 -> T&I NZ National Operations | S6: ='FY26 Revenue'!C6 -> T&I NZ National Operations | T6: ='FY26 Revenue'!M6 -> 13
A7: 37395 | B7: Downer | C7: ='FY26 Revenue'!N7 -> REV_Transport & Infrastructure NZ | D7: =_xlfn.XLOOKUP(C7,'Extract_for_Locations 1 Oct 25'!B:B,'Extract_for_Locations 1 Oct 25'!E:E) -> L9.DNZJ.8134 | E7: 7868 | F7: Revenue - AUD Million | H7: =CONCATENATE("FY26REV_",'FY26 Revenue'!B7) -> FY26REV_Transport & Infrastructure NZ | I7: =CONCATENATE("FY26REV_",'FY26 Revenue'!B7) -> FY26REV_Transport & Infrastructure NZ | J7: Downer | K7: Revenue | L7: 46113 | M7: 46142 | N7: Actual | O7: Standard | Q7: Insert | R7: ='FY26 Revenue'!C7 -> T&I NZ Overheads | S7: ='FY26 Revenue'!C7 -> T&I NZ Overheads | T7: ='FY26 Revenue'!M7 -> 0.1
A8: 37395 | B8: Downer | C8: ='FY26 Revenue'!N8 -> REV_Transport & Infrastructure AU | D8: =_xlfn.XLOOKUP(C8,'Extract_for_Locations 1 Oct 25'!B:B,'Extract_for_Locations 1 Oct 25'!E:E) -> L9.J.170615 | E8: 7868 | F8: Revenue - AUD Million | H8: =CONCATENATE("FY26REV_",'FY26 Revenue'!B8) -> FY26REV_Transport & Infrastructure AU | I8: =CONCATENATE("FY26REV_",'FY26 Revenue'!B8) -> FY26REV_Transport & Infrastructure AU | J8: Downer | K8: Revenue | L8: 46113 | M8: 46142 | N8: Actual | O8: Standard | Q8: Insert | R8: ='FY26 Revenue'!C8 -> T&I AU Asphalt & Products | S8: ='FY26 Revenue'!C8 -> T&I AU Asphalt & Products | T8: ='FY26 Revenue'!M8 -> 76.6
A9: 37395 | B9: Downer | C9: ='FY26 Revenue'!N9 -> REV_Transport & Infrastructure AU | D9: =_xlfn.XLOOKUP(C9,'Extract_for_Locations 1 Oct 25'!B:B,'Extract_for_Locations 1 Oct 25'!E:E) -> L9.J.170615 | E9: 7868 | F9: Revenue - AUD Million | H9: =CONCATENATE("FY26REV_",'FY26 Revenue'!B9) -> FY26REV_Transport & Infrastructure AU | I9: =CONCATENATE("FY26REV_",'FY26 Revenue'!B9) -> FY26REV_Transport & Infrastructure AU | J9: Downer | K9: Revenue | L9: 46113 | M9: 46142 | N9: Actual | O9: Standard | Q9: Insert | R9: ='FY26 Revenue'!C9 -> Maintenance & ITS | S9: ='FY26 Revenue'!C9 -> Maintenance & ITS | T9: ='FY26 Revenue'!M9 -> 44.9
A10: 37395 | B10: Downer | C10: ='FY26 Revenue'!N10 -> REV_Transport & Infrastructure AU | D10: =_xlfn.XLOOKUP(C10,'Extract_for_Locations 1 Oct 25'!B:B,'Extract_for_Locations 1 Oct 25'!E:E) -> L9.J.170615 | E10: 7868 | F10: Revenue - AUD Million | H10: =CONCATENATE("FY26REV_",'FY26 Revenue'!B10) -> FY26REV_Transport & Infrastructure AU | I10: =CONCATENATE("FY26REV_",'FY26 Revenue'!B10) -> FY26REV_Transport & Infrastructure AU | J10: Downer | K10: Revenue | L10: 46113 | M10: 46142 | N10: Actual | O10: Standard | Q10: Insert | R10: ='FY26 Revenue'!C10 -> Pavement Rehabilitation & Civils | S10: ='FY26 Revenue'!C10 -> Pavement Rehabilitation & Civils | T10: ='FY26 Revenue'!M10 -> 8.9
A11: 37395 | B11: Downer | C11: ='FY26 Revenue'!N11 -> REV_Transport & Infrastructure AU | D11: =_xlfn.XLOOKUP(C11,'Extract_for_Locations 1 Oct 25'!B:B,'Extract_for_Locations 1 Oct 25'!E:E) -> L9.J.170615 | E11: 7868 | F11: Revenue - AUD Million | H11: =CONCATENATE("FY26REV_",'FY26 Revenue'!B11) -> FY26REV_Transport & Infrastructure AU | I11: =CONCATENATE("FY26REV_",'FY26 Revenue'!B11) -> FY26REV_Transport & Infrastructure AU | J11: Downer | K11: Revenue | L11: 46113 | M11: 46142 | N11: Actual | O11: Standard | Q11: Insert | R11: ='FY26 Revenue'!C11 -> Specialised Pavements & Projects | S11: ='FY26 Revenue'!C11 -> Specialised Pavements & Projects | T11: ='FY26 Revenue'!M11 -> 3.6
A12: 37395 | B12: Downer | C12: ='FY26 Revenue'!N12 -> REV_Transport & Infrastructure AU | D12: =_xlfn.XLOOKUP(C12,'Extract_for_Locations 1 Oct 25'!B:B,'Extract_for_Locations 1 Oct 25'!E:E) -> L9.J.170615 | E12: 7868 | F12: Revenue - AUD Million | H12: =CONCATENATE("FY26REV_",'FY26 Revenue'!B12) -> FY26REV_Transport & Infrastructure AU | I12: =CONCATENATE("FY26REV_",'FY26 Revenue'!B12) -> FY26REV_Transport & Infrastructure AU | J12: Downer | K12: Revenue | L12: 46113 | M12: 46142 | N12: Actual | O12: Standard | Q12: Insert | R12: ='FY26 Revenue'!C12 -> Thin Surfacing | S12: ='FY26 Revenue'!C12 -> Thin Surfacing | T12: ='FY26 Revenue'!M12 -> 35.1
A13: 37395 | B13: Downer | C13: ='FY26 Revenue'!N13 -> REV_Transport & Infrastructure AU | D13: =_xlfn.XLOOKUP(C13,'Extract_for_Locations 1 Oct 25'!B:B,'Extract_for_Locations 1 Oct 25'!E:E) -> L9.J.170615 | E13: 7868 | F13: Revenue - AUD Million | H13: =CONCATENATE("FY26REV_",'FY26 Revenue'!B13) -> FY26REV_Transport & Infrastructure AU | I13: =CONCATENATE("FY26REV_",'FY26 Revenue'!B13) -> FY26REV_Transport & Infrastructure AU | J13: Downer | K13: Revenue | L13: 46113 | M13: 46142 | N13: Actual | O13: Standard | Q13: Insert | R13: ='FY26 Revenue'!C13 -> BIA | S13: ='FY26 Revenue'!C13 -> BIA | T13: ='FY26 Revenue'!M13 -> 10.2
... A80: 37395 | B80: Downer | C80: ='FY26 Revenue'!N80 -> REV_Intra Elim | D80: =_xlfn.XLOOKUP(C80,'Extract_for_Locations 1 Oct 25'!B:B,'Extract_for_Locations 1 Oct 25'!E:E) -> CORIE | E80: 7868 | F80: Revenue - AUD Million | H80: =CONCATENATE("FY26REV_",'FY26 Revenue'!B80) -> FY26REV_Intra Elim | I80: =CONCATENATE("FY26REV_",'FY26 Revenue'!B80) -> FY26REV_Intra Elim | J80: Downer | K80: Revenue | L80: 46113 | M80: 46142 | N80: Actual | O80: Standard | Q80: Insert | R80: ='FY26 Revenue'!C80 -> Intra Elim | S80: ='FY26 Revenue'!C80 -> Intra Elim | T80: ='FY26 Revenue'!M80 -> -0.1

Sheet FY26 Revenue
A1: Entity Name/Division | B1: UD1 Name/Sub-LOB | C1: UD1 Name/Sub-LOB Level 2 | D1: Jul | E1: Aug | F1: Sep | G1: Oct | H1: Nov | I1: Dec | J1: Jan | K1: Feb | L1: Mar | M1: Apr | N1: Location Name
A2: Transport & Infrastructure | B2: Transport & Infrastructure NZ | C2: T&I NZ North | D2: 30.3 | E2: 30.4 | F2: 33.6 | G2: 41.8 | H2: 49 | I2: 39.2 | J2: 37.1 | K2: 54.6 | L2: 53.1 | M2: 44.2 | N2: =CONCATENATE("REV","_",Table2[[#This Row],[UD1 Name/Sub-LOB]]) -> REV_Transport & Infrastructure NZ
A3: Transport & Infrastructure | B3: Transport & Infrastructure NZ | C3: T&I NZ South | D3: 27.8 | E3: 28 | F3: 31.5 | G3: 39.3 | H3: 45.5 | I3: 37.3 | J3: 31.5 | K3: 46.3 | L3: 54.8 | M3: 42.8 | N3: =CONCATENATE("REV","_",Table2[[#This Row],[UD1 Name/Sub-LOB]]) -> REV_Transport & Infrastructure NZ
A4: Transport & Infrastructure | B4: Transport & Infrastructure NZ | C4: T&I NZ Infrastructure Delivery | D4: 24.6 | E4: 28.1 | F4: 35.3 | G4: 34.3 | H4: 37.8 | I4: 39.2 | J4: 20.3 | K4: 30.4 | L4: 30.6 | M4: 33.5 | N4: =CONCATENATE("REV","_",Table2[[#This Row],[UD1 Name/Sub-LOB]]) -> REV_Transport & Infrastructure NZ
A5: Transport & Infrastructure | B5: Transport & Infrastructure NZ | C5: T&I NZ Hawkins | D5: 41.4 | E5: 44.3 | F5: 47.1 | G5: 49.2 | H5: 47.1 | I5: 44.7 | J5: 35.6 | K5: 43 | L5: 54.5 | M5: 51 | N5: =CONCATENATE("REV","_",Table2[[#This Row],[UD1 Name/Sub-LOB]]) -> REV_Transport & Infrastructure NZ
A6: Transport & Infrastructure | B6: Transport & Infrastructure NZ | C6: T&I NZ National Operations | D6: 8.8 | E6: 9.5 | F6: 9.6 | G6: 11.1 | H6: 15.4 | I6: 12.7 | J6: 9.8 | K6: 15.1 | L6: 15.7 | M6: 13 | N6: =CONCATENATE("REV","_",Table2[[#This Row],[UD1 Name/Sub-LOB]]) -> REV_Transport & Infrastructure NZ
A7: Transport & Infrastructure | B7: Transport & Infrastructure NZ | C7: T&I NZ Overheads | D7: 0 | E7: 0 | F7: 0.5 | G7: 0.9 | H7: -0.8 | I7: -0.8 | J7: 0.1 | K7: 0.2 | L7: 0.3 | M7: 0.1 | N7: =CONCATENATE("REV","_",Table2[[#This Row],[UD1 Name/Sub-LOB]]) -> REV_Transport & Infrastructure NZ
A8: Transport & Infrastructure | B8: Transport & Infrastructure AU | C8: T&I AU Asphalt & Products | D8: 50.2 | E8: 42.9 | F8: 53.2 | G8: 51.8 | H8: 58.5 | I8: 48.6 | J8: 45 | K8: 60.1 | L8: 70.3 | M8: 76.6 | N8: =CONCATENATE("REV","_",Table2[[#This Row],[UD1 Name/Sub-LOB]]) -> REV_Transport & Infrastructure AU
A9: Transport & Infrastructure | B9: Transport & Infrastructure AU | C9: Maintenance & ITS | D9: 26.2 | E9: 27.2 | F9: 28.6 | G9: 36 | H9: 33.4 | I9: 30.2 | J9: 25.6 | K9: 35.6 | L9: 38.5 | M9: 44.9 | N9: =CONCATENATE("REV","_",Table2[[#This Row],[UD1 Name/Sub-LOB]]) -> REV_Transport & Infrastructure AU
A10: Transport & Infrastructure | B10: Transport & Infrastructure AU | C10: Pavement Rehabilitation & Civils | D10: 0.7 | E10: 0.8 | F10: 1.8 | G10: 3.3 | H10: 6.3 | I10: 5.4 | J10: 4.5 | K10: 6.6 | L10: 9.3 | M10: 8.9 | N10: =CONCATENATE("REV","_",Table2[[#This Row],[UD1 Name/Sub-LOB]]) -> REV_Transport & Infrastructure AU
A11: Transport & Infrastructure | B11: Transport & Infrastructure AU | C11: Specialised Pavements & Projects | D11: 6.8 | E11: 7.3 | F11: 6.3 | G11: 5.6 | H11: 5.1 | I11: 3.2 | J11: 2.9 | K11: 6.7 | L11: 3.7 | M11: 3.6 | N11: =CONCATENATE("REV","_",Table2[[#This Row],[UD1 Name/Sub-LOB]]) -> REV_Transport & Infrastructure AU
A12: Transport & Infrastructure | B12: Transport & Infrastructure AU | C12: Thin Surfacing | D12: 18.5 | E12: 22.1 | F12: 32.6 | G12: 47 | H12: 36 | I12: 30.2 | J12: 25.2 | K12: 33.7 | L12: 37.2 | M12: 35.1 | N12: =CONCATENATE("REV","_",Table2[[#This Row],[UD1 Name/Sub-LOB]]) -> REV_Transport & Infrastructure AU
A13: Transport & Infrastructure | B13: Transport & Infrastructure AU | C13: BIA | D13: 4 | E13: 2.2 | F13: 5.5 | G13: 5.2 | H13: 5.8 | I13: 4.8 | J13: 5 | K13: 5.5 | L13: 5.8 | M13: 10.2 | N13: =CONCATENATE("REV","_",Table2[[#This Row],[UD1 Name/Sub-LOB]]) -> REV_Transport & Infrastructure AU
... A80: Intra Elim | B80: Intra Elim | C80: Intra Elim | D80: -0.1 | E80: -0.1 | F80: -0.1 | G80: 0.2 | H80: -0.1 | I80: -0.2 | J80: 0.2 | K80: 0.2 | L80: 0.1 | M80: -0.1 | N80: =CONCATENATE("REV","_",Table2[[#This Row],[UD1 Name/Sub-LOB]]) -> REV_Intra Elim
M81: =SUM(M2:M80) -> 847.9

Sheet Extract_for_Locations 1 Oct 25
A1: Associate | B1: Location_Name | C1: Type | D1: Ref_No | E1: Location Ref | F1: Id | G1: Notes | H1: Address | I1: City | J1: State | K1: Postal_Code | L1: Address Country | M1: Region | N1: Country | O1: Alternate Factor Region | P1: Group Level 1 | Q1: Group Level 2 | R1: Group Level 3 | S1: Group_Associate | T1: Report_Percent | U1: Effective_From | V1: Effective_To | W1: Group_Type | X1: Latitude | Y1: Longitude | Z1: ANZSIC Code | AA1: Opened On | AB1: Closed On
A2: Downer | B2: [CLOSED] Hobart Airport Upgrade Project | C2: Airport | D2: L9.J.170751 | E2: 170751 | G2: TI-170751 - Airports General Delivery | H2: 250 Surf Road, Seven Mile Beach | I2: Tasmania | J2: TAS | K2: 7170 | M2: Tasmania | N2: Australia | P2: Operational Control | Q2: Operational Control | R2: Transport & Infrastructure (T&I) | S2: Downer | T2: 100 | W2: Classification | AB2: 45808
A3: Downer | B3: _CLOSED_ AGIS Braddon | C3: Office | D3: L9.J.502002 | E3: 2001 | F3: 2001 | G3: electricity data only from landlord accounts | M3: Australian Capital Territory | N3: Australia | P3: Operational Control | Q3: Operational Control | R3: Social Infra & Citizen Serv (SICS) | S3: Downer | T3: 100 | U3: 43405 | V3: 44500 | W3: Classification | X3: -35.273 | Y3: 149.133 | Z3: 760 | AA3: 42583 | AB3: 44901
A4: Downer | B4: _CLOSED_ OSM_Waitaki | C4: Other | D4: L9.DNZJ.55876 | E4: 5088 | G4: Outside Space Management (Gardening) - New facilities established for more granular reporting and to reflect new structure for FY17. See facility named "NZ-Infrastructure Services" for historical data. | H4: Chelmer Street | I4: Oamaru | J4: Otago | K4: 2104 | L4: New Zealand | M4: Oamaru | N4: New Zealand | P4: Operational Control | Q4: Operational Control | R4: Transport & Infrastructure (T&I) | S4: Downer | T4: 100 | W4: Classification | X4: -45.097848 | Y4: 170.9607 | Z4: 731 | AA4: 42917
A5: Downer | B5: _CLOSED_25820008 - Winneke Main Substation Switchboard Replacement | C5: Site | D5: L9.J.25820008 | E5: UTIL-25820008 | G5: Main Substation Switchboard Replacement - Project finished in September 2022. | M5: Victoria | N5: Australia | P5: Operational Control | Q5: Operational Control | R5: Energy and Utilities (EU) | S5: Downer | T5: 100 | W5: Classification | AB5: 44835
A6: Downer | B6: _CLOSED_25820012 - WTP 25W Lagoon Pond 1 HV and LV Renewals | C6: Site | D6: L9.J.25820012 | E6: UTIL-25820012 | G6: WTP 25W Lagoon Pond 1 HV and LV Renewals | M6: Victoria | N6: Australia | P6: Operational Control | Q6: Operational Control | R6: Energy and Utilities (EU) | S6: Downer | T6: 100 | W6: Classification | AB6: 45629
A7: Downer | B7: _CLOSED_86 Collins St Tas | C7: Branch Office | D7: L9.J.105001 | E7: 9164 | G7: Level 12, 86 Collins Street HOBART TAS 7000 | M7: Hobart | N7: Australia | P7: Operational Control | Q7: Operational Control | R7: Corporate | S7: Downer | T7: 100 | W7: Classification | Z7: 692
A8: Downer | B8: _CLOSED_Accommodation - NZ | C8: Hotel | D8: L9.WAU.000887 | E8: L9.WAU.000887 | M8: Auckland | N8: New Zealand | P8: Operational Control | Q8: Operational Control | R8: Corporate | S8: Downer | T8: 100 | W8: Classification
A9: Downer | B9: _CLOSED_ACES - North Queensland Region | C9: Depot | D9: L9.DUA.12005 | E9: L9.DUA.12005 | G9: Contract ended June 2022. | M9: Queensland | N9: Australia | P9: Operational Control | Q9: Operational Control | R9: Energy and Utilities (EU) | S9: Downer | T9: 100 | W9: Classification | AB9: 44742
A10: Downer | B10: _CLOSED_Adelaide Light Rail - North Terrace Tramli | C10: Other | D10: L9.D.20143004 | E10: L9.D.20143004 | H10: SA | I10: Adelaide | J10: SA | M10: South Australia | N10: Australia | P10: Operational Control | Q10: Operational Control | R10: DT Infrastructure (pre Sept 23 divestment) | S10: Downer | T10: 100 | V10: 45199 | W10: Classification | X10: -34.921297 | Y10: 138.60466 | Z10: 310
A11: Downer | B11: _CLOSED_AE Smith - Burleigh | C11: Branch Office | D11: L9.S.13000757 | E11: 9165 | G11: 12/8 Fortitude Crescent BURLEIGH HEADS QLD 4220 | M11: New South Wales | N11: Australia | P11: Operational Control | Q11: Operational Control | R11: Asset & Development Services (Baseline) | S11: Downer | T11: 100 | V11: 45107 | W11: Classification | Z11: 692
A12: Downer | B12: _CLOSED_AE Smith - Eagle Farm | C12: Branch Office | D12: L9.S.16015125 | E12: 9013 | H12: Lot 801 65 Links Ave | I12: Eagle Farm | J12: QLD | K12: 4009 | M12: Queensland | N12: Australia | P12: Operational Control | Q12: Operational Control | R12: Asset & Development Services (Baseline) | S12: Downer | T12: 100 | V12: 45107 | W12: Classification | X12: -27.436443 | Y12: 153.08637 | Z12: 692
A13: Downer | B13: _CLOSED_AE Smith - Eagle Farm, Harvey St | C13: Office | D13: L9.S.13001004 | E13: 9128 | H13: Harvey St | I13: Eagle Farm | J13: QLD | K13: 4009 | M13: Brisbane | N13: Australia | P13: Operational Control | Q13: Operational Control | R13: Asset & Development Services (Baseline) | S13: Downer | T13: 100 | V13: 45107 | W13: Classification | X13: -27.437252 | Y13: 153.09361 | Z13: 692
A14: Downer | B14: _CLOSED_AE Smith - Eagle Farm, Schneider Rd | C14: Branch Office | D14: L9.S.13001052 | E14: 9127 | H14: 80 Schneider Road | I14: Eagle Farm | J14: QLD | K14: 4009 | L14: Australia | M14: Brisbane | N14: Australia | P14: Operational Control | Q14: Operational Control | R14: Asset & Development Services (Baseline) | S14: Downer | T14: 100 | V14: 45107 | W14: Classification | X14: -27.423892 | Y14: 153.08506 | Z14: 692
A15: Downer | B15: _CLOSED_AE Smith - Mornington | C15: Branch Office | D15: L9.S.13001061 | E15: 9014 | H15: U 2 4 Yamada Place | I15: Mornington | J15: TAS | K15: 7018 | L15: Australia | M15: Tasmania | N15: Australia | P15: Operational Control | Q15: Operational Control | R15: Asset & Development Services (Baseline) | S15: Downer | T15: 100 | V15: 45107 | W15: Classification | X15: -42.862696 | Y15: 147.3998 | Z15: 692
A16: Downer | B16: _CLOSED_AE Smith - Mulgrave | C16: Branch Office | D16: L9.S.16015131 | E16: 9016 | G16: Lease ended 2/12/2021 | H16: 21-29 Miles St | I16: Mulgrave | J16: VIC | K16: 3170 | M16: Mulgrave | N16: Australia | P16: Operational Control | Q16: Operational Control | R16: Asset & Development Services (Baseline) | S16: Downer | T16: 100 | V16: 45107 | W16: Classification | X16: -37.923024 | Y16: 145.15337 | Z16: 692
A17: Downer | B17: _CLOSED_AE Smith - Scoresby | C17: Branch Office | D17: L9.S.13001039 | E17: 9018 | H17: 20-22 Janine St | I17: Scoresby | J17: VIC | K17: 3179 | M17: Victoria | N17: Australia | P17: Operational Control | Q17: Operational Control | R17: Asset & Development Services (Baseline) | S17: Downer | T17: 100 | V17: 45107 | W17: Classification | X17: -37.900965 | Y17: 145.23027 | Z17: 692
A18: Downer | B18: _CLOSED_Aldoga TL - Site | C18: Site | D18: L9.J.37740112 | M18: Queensland | N18: Australia | P18: Operational Control | Q18: Operational Control | R18: Energy and Utilities (EU) | S18: Downer | T18: 100 | W18: Classification | AB18: 45112
A19: Downer | B19: _CLOSED_Anglo TXL | C19: Site | D19: L9.J.37240023 | E19: 37240023 | M19: Moranbah | N19: Australia | P19: Operational Control | Q19: Operational Control | R19: Energy and Utilities (EU) | S19: Downer | T19: 100 | W19: Classification | Z19: 310 | AA19: 45266 | AB19: 45577
A20: Downer | B20: _CLOSED_APA SA | C20: Depot | D20: L9.J.24170135 | E20: L9.J.24170135 | G20: Duplicate location of Gepps Cross. (Part of the SA Gas business office) | M20: South Australia | N20: Australia | P20: Operational Control | Q20: Operational Control | R20: Energy and Utilities (EU) | S20: Downer | T20: 100 | W20: Classification | AB20: 44742
A21: Downer | B21: _CLOSED_Asphalt _Whangarei | C21: Other | D21: L9.DNZJ.3502 | E21: 5010 | G21: Production of materials for road construction - New facilities established for more granular reporting and to reflect new structure for FY17. See facility named "NZ-Products" for historical data. | H21: 116-118 Port Road | I21: Whangarei | J21: Northland | K21: 9016 | L21: New Zealand | M21: Whangarei | N21: New Zealand | P21: Operational Control | Q21: Operational Control | R21: Transport & Infrastructure (T&I) | S21: Downer | T21: 100 | U21: 1899/12/31 | W21: Classification | X21: -35.743169 | Y21: 174.34159 | Z21: 310 | AA21: 42917
A22: Downer | B22: _CLOSED_Asphalt Prod - Mowbray (OLD) | C22: Asphalt Plant | D22: L9.J.170360 | E22: 182 | G22: previously used L9.J.17030565, which has now transferred to New Mowbray Asphalt Envizi location. Replaced with L9.J.170360 | H22: Remount Road | I22: Mowbray | J22: TAS | K22: 7248 | L22: Australia | M22: Tasmania | N22: Australia | P22: Operational Control | Q22: Operational Control | R22: Transport & Infrastructure (T&I) | S22: Downer | T22: 100 | W22: Classification | X22: -41.399 | Y22: 147.162 | Z22: 170
A23: Downer | B23: _CLOSED_Asphalt Prod - Rosehill (OLD) | C23: Asphalt Plant | D23: L9.J.17010964 | E23: 248 | G23: Vacated this location at the end of June 2022 and shifted operations to Rosehill - Devon St. Please refer to attachments for further information. | H23: 1 Unwin Street | I23: Rosehill | J23: NSW | K23: 2142 | L23: Australia | M23: Lidcombe | N23: Australia | P23: Operational Control | Q23: Operational Control | R23: Transport & Infrastructure (T&I) | S23: Downer | T23: 100 | W23: Classification | X23: -33.828 | Y23: 151.023 | Z23: 170 | AB23: 44985
A24: Downer | B24: _CLOSED_Asphalt_Auckland | C24: Other | D24: L9.DNZJ.3503 | E24: 5011 | G24: Production of materials for road construction - New facilities established for more granular reporting and to reflect new structure for FY17. See facility named "NZ-Products" for historical data. | H24: 645 Great South Rd, Penrose | I24: Auckland | J24: Auckland | K24: 3200 | L24: New Zealand | M24: Panmure | N24: New Zealand | P24: Operational Control | Q24: Operational Control | R24: Transport & Infrastructure (T&I) | S24: Downer | T24: 100 | U24: 1899/12/31 | W24: Classification | X24: -36.915214 | Y24: 174.82028 | Z24: 310 | AA24: 42917
A25: Downer | B25: _CLOSED_Asphalt_Dunedin | C25: Other | D25: L9.DNZJ.3508 | E25: 5012 | G25: Production of materials for road construction - New facilities established for more granular reporting and to reflect new structure for FY17. See facility named "NZ-Products" for historical data. | H25: 102 Parry Street | I25: Dunedin | J25: Otago | K25: 9810 | L25: New Zealand | M25: Dunedin | N25: New Zealand | P25: Operational Control | Q25: Operational Control | R25: Transport & Infrastructure (T&I) | S25: Downer | T25: 100 | U25: 1899/12/31 | W25: Classification | X25: -45.869839 | Y25: 170.53156 | Z25: 310 | AA25: 42917
A26: Downer | B26: _CLOSED_Asphalt_Hamilton | C26: Other | D26: L9.DNZJ.3504 | E26: 5013 | G26: Production of materials for road construction - New facilities established for more granular reporting and to reflect new structure for FY17. See facility named "NZ-Products" for historical data. | H26: 16 Manchester Place, Te Rapa | I26: Hamilton | J26: Waikato | K26: 4312 | L26: New Zealand | M26: Hamilton | N26: New Zealand | P26: Operational Control | Q26: Operational Control | R26: Transport & Infrastructure (T&I) | S26: Downer | T26: 100 | U26: 1899/12/31 | W26: Classification | X26: -37.754068 | Y26: 175.23706 | Z26: 310 | AA26: 42917
A27: Downer | B27: _CLOSED_Asphalt_Invercargill | C27: Other | D27: L9.DNZJ.3509 | E27: 5014 | G27: Production of materials for road construction - New facilities established for more granular reporting and to reflect new structure for FY17. See facility named "NZ-Products" for historical data. | H27: 210 Mersey Street, Invercargill West | I27: Invercargill | J27: Southland | K27: 6035 | L27: New Zealand | M27: Invercargill | N27: New Zealand | P27: Operational Control | Q27: Operational Control | R27: Transport & Infrastructure (T&I) | S27: Downer | T27: 100 | U27: 1899/12/31 | W27: Classification | X27: -46.415219 | Y27: 168.34171 | Z27: 310 | AA27: 42917
A28: Downer | B28: _CLOSED_Asphalt_Isacc-JV | C28: Industrial | D28: L9.DNZJ.3098 | E28: 5294 | G28: Production of materials for road construction - New facilities established for more granular reporting and to reflect new structure for FY19 | M28: Christchurch | N28: New Zealand | P28: Operational Control | Q28: Operational Control | R28: Transport & Infrastructure (T&I) | S28: Downer | T28: 100 | U28: 1899/12/31 | W28: Classification | Z28: 310
A29: Downer | B29: _CLOSED_Asphalt_Mobile | C29: Asphalt Plant | D29: L9.DNZJ.3512 | E29: 5286 | G29: Mobile Asphalt plant relocated across NZ depending on contracts - assigned to head office as main location | M29: Auckland City | N29: New Zealand | P29: Operational Control | Q29: Operational Control | R29: Transport & Infrastructure (T&I) | S29: Downer | T29: 100 | U29: 1899/12/31 | W29: Classification
A30: Downer | B30: _CLOSED_Asphalt_New Plymouth | C30: Other | D30: L9.DNZJ.3505 | E30: 5015 | G30: Production of materials for road construction - New facilities established for more granular reporting and to reflect new structure for FY17. See facility named "NZ-Products" for historical data. | H30: 106 Rifle Range Rd, Waiwhakaiho | I30: New Plymouth | J30: Taranaki | K30: 9814 | L30: New Zealand | M30: New Plymouth | N30: New Zealand | P30: Operational Control | Q30: Operational Control | R30: Transport & Infrastructure (T&I) | S30: Downer | T30: 100 | U30: 1899/12/31 | W30: Classification | X30: -39.042342 | Y30: 174.11917 | Z30: 310 | AA30: 42917
A31: Downer | B31: _CLOSED_Asphalt_Wellington | C31: Other | D31: L9.DNZJ.3507 | E31: 5016 | G31: Production of materials for road construction - New facilities established for more granular reporting and to reflect new structure for FY17. See facility named "NZ-Products" for historical data. | H31: Kiwi Point, 137 Centennial Highway, Ngauranga | I31: Wellington | J31: Wellington | K31: 8082 | L31: New Zealand | M31: Wellington | N31: New Zealand | P31: Operational Control | Q31: Operational Control | R31: Transport & Infrastructure (T&I) | S31: Downer | T31: 100 | U31: 1899/12/31 | W31: Classification | X31: -41.237631 | Y31: 174.80509 | Z31: 310 | AA31: 42917
A32: Downer | B32: _CLOSED_Bango Wind Farm | C32: Other | D32: L9.J.37750008 | E32: IP-37750008 | G32: Operational control. Changed from Ref No 7040 | M32: New South Wales | N32: Australia | P32: Operational Control | Q32: Operational Control | R32: Energy and Utilities (EU) | S32: Downer | T32: 100 | W32: Classification
A33: Downer | B33: _CLOSED_Beryl Solar Farm Construction Project | C33: Other | D33: L9.J.37110018 | E33: 7037 | H33: 39 Dehli Road | I33: North Ryde | J33: NSW | K33: 2113 | L33: Australia | M33: Gulgong | N33: Australia | P33: Operational Control | Q33: Operational Control | R33: Energy and Utilities (EU) | S33: Downer | T33: 100 | W33: Classification | X33: -33.79982 | Y33: 151.14323 | Z33: 310
A34: Downer | B34: _CLOSED_Bitumen_Bluff | C34: Other | D34: L9.DNZJ.3042 | E34: 5017 | G34: Storage and sale of Bitumen, Production and sale of Cutback Bitumen, Polymer Modified Bitumen and Bitumen Emulsions - New facilities established for more granular reporting and to reflect new structure for FY17. See facility named "NZ-Products" for historical data. | H34: 50 Foreshore Rd | I34: Bluff | J34: Southland | K34: 3116 | L34: New Zealand | M34: Bluff | N34: New Zealand | P34: Operational Control | Q34: Operational Control | R34: Transport & Infrastructure (T&I) | S34: Downer | T34: 100 | U34: 1899/12/31 | W34: Classification | X34: -46.597975 | Y34: 168.34254 | Z34: 170 | AA34: 42917
A35: Downer | B35: _CLOSED_Bitumen_Emulco-JV | C35: Industrial | D35: L9.DNZJ.3099 | E35: 5296 | G35: Production of materials for road construction - New facilities established for more granular reporting and to reflect new structure for FY19 | M35: Rotorua | N35: New Zealand | P35: Operational Control | Q35: Operational Control | R35: Transport & Infrastructure (T&I) | S35: Downer | T35: 100 | U35: 1899/12/31 | W35: Classification | Z35: 310
A36: Downer | B36: _CLOSED_Bitumen_Lyttelton | C36: Other | D36: L9.DNZJ.3041 | E36: 5018 | G36: Storage and sale of Bitumen, Production and sale of Cutback Bitumen, Polymer Modified Bitumen and Bitumen Emulsions - New facilities established for more granular reporting and to reflect new structure for FY17. See facility named "NZ-Products" for historical data. | H36: Lyttelton Bitumen Terminal Charlotte Jane Quay, Port Lyttelton | I36: Lyttelton | J36: Canterbury | K36: 4340 | L36: New Zealand | M36: Christchurch | N36: New Zealand | P36: Operational Control | Q36: Operational Control | R36: Transport & Infrastructure (T&I) | S36: Downer | T36: 100 | U36: 1899/12/31 | W36: Classification | X36: -43.610561 | Y36: 172.70419 | Z36: 170 | AA36: 42917
A37: Downer | B37: _CLOSED_Bitumen_Mt Maunganui | C37: Other | D37: L9.DNZJ.3040 | E37: 5019 | G37: Storage and sale of Bitumen, Production and sale of Cutback Bitumen, Polymer Modified Bitumen and Bitumen Emulsions - New facilities established for more granular reporting and to reflect new structure for FY17. See facility named "NZ-Products" for historical data. | H37: 198 Totara Street, Mt Maunganui | I37: Tauranga | J37: Bay of Plenty | K37: 3116 | L37: New Zealand | M37: Tauranga | N37: New Zealand | P37: Operational Control | Q37: Operational Control | R37: Transport & Infrastructure (T&I) | S37: Downer | T37: 100 | U37: 1899/12/31 | W37: Classification | X37: -37.663866 | Y37: 176.18689 | Z37: 170 | AA37: 42917
A38: Downer | B38: _CLOSED_Bitumen_Taranaki | C38: Other | D38: L9.DNZJ.3045 | E38: 5020 | G38: Storage and sale of Bitumen, Production and sale of Cutback Bitumen, Polymer Modified Bitumen and Bitumen Emulsions - New facilities established for more granular reporting and to reflect new structure for FY17. See facility named "NZ-Products" for historical data. | H38: 1 Wharf Street, Port Taranaki | I38: New Plymouth | J38: Taranaki | K38: 9230 | L38: New Zealand | M38: New Plymouth | N38: New Zealand | P38: Operational Control | Q38: Operational Control | R38: Transport & Infrastructure (T&I) | S38: Downer | T38: 100 | U38: 1899/12/31 | W38: Classification | X38: -39.057799 | Y38: 174.03126 | Z38: 170 | AA38: 42917
A39: Downer | B39: _CLOSED_Bitumen_Transport | C39: Other | D39: L9.DNZJ.3010 | E39: 5021 | G39: Transport of Bitumen to customers - New facilities established for more granular reporting and to reflect new structure for FY17. See facility named "NZ-Products" for historical data. | H39: 9 Owens Place, Mt Maunganui | I39: Tauranga | J39: Bay of Plenty | K39: 7201 | L39: New Zealand | M39: Tauranga | N39: New Zealand | P39: Operational Control | Q39: Operational Control | R39: Transport & Infrastructure (T&I) | S39: Downer | T39: 100 | U39: 1899/12/31 | W39: Classification | X39: -37.678294 | Y39: 176.22236 | Z39: 461 | AA39: 42917
A40: Downer | B40: _CLOSED_BP_Auckland_Cordis Hotel | C40: Construction Site | D40: L9.DNZ.HA0383 | E40: 5309 | M40: Auckland | N40: New Zealand | P40: Operational Control | Q40: Operational Control | R40: Transport & Infrastructure (T&I) | S40: Downer | T40: 100 | W40: Classification
A41: Downer | B41: _CLOSED_BP_Auckland_Counties Manukau AMHU STG 2 | C41: Construction Site | D41: L9.DNZ.HA0384 | E41: 5310 | M41: Auckland | N41: New Zealand | P41: Operational Control | Q41: Operational Control | R41: Transport & Infrastructure (T&I) | S41: Downer | T41: 100 | W41: Classification
A42: Downer | B42: _CLOSED_BP_Auckland_FSNI Head Office | C42: Construction Site | D42: L9.DNZ.HA0385 | E42: 5311 | M42: Auckland | N42: New Zealand | P42: Operational Control | Q42: Operational Control | R42: Transport & Infrastructure (T&I) | S42: Downer | T42: 100 | W42: Classification
A43: Downer | B43: _CLOSED_BP_Auckland_POA Car Handling Facility | C43: Construction Site | D43: L9.DNZ.HA0382 | E43: 5308 | M43: Auckland | N43: New Zealand | P43: Operational Control | Q43: Operational Control | R43: Transport & Infrastructure (T&I) | S43: Downer | T43: 100 | U43: 1899/12/31 | W43: Classification
A44: Downer | B44: _CLOSED_BP_Auckland_Small Jobs | C44: Operations Center | D44: L9.DNZ.COR | E44: 5255 | G44: Projects located at numerous sites throughout Auckland Region - New location established following purchase of Hawkins 2017 | M44: Auckland City | N44: New Zealand | P44: Operational Control | Q44: Operational Control | R44: Transport & Infrastructure (T&I) | S44: Downer | T44: 100 | W44: Classification
A45: Downer | B45: _CLOSED_BP_Central_Farmers Tauranga | C45: Construction Site | D45: L9.DNZ.HC0331 | E45: 5256 | G45: Project Site - Building Construction - New location established in FY19 | M45: Tauranga | N45: New Zealand | P45: Operational Control | Q45: Operational Control | R45: Transport & Infrastructure (T&I) | S45: Downer | T45: 100 | W45: Classification
A46: Downer | B46: _CLOSED_BP_Central_Kawerau Geothermal Switchroom | C46: Other | D46: L9.DNZ.PLT | E46: 5205 | G46: Project Site - Building Construction - New location established following purchase of Hawkins 2037 - Ormat Pacific | H46: Old Coach Road, Paengaroa | I46: Rotorua | J46: Bay of Plenty | K46: 3110 | L46: New Zealand | M46: Paengaroa | N46: New Zealand | P46: Operational Control | Q46: Operational Control | R46: Transport & Infrastructure (T&I) | S46: Downer | T46: 100 | W46: Classification | X46: -37.838121 | Y46: 176.42131 | Z46: 302 | AA46: 42954 | AB46: 43190
A47: Downer | B47: _CLOSED_BP_Central_RHO-Hamilton | C47: Other | D47: L9.DNZ.CEN | E47: 5196 | G47: Support services for projects located at numerous sites throughout Central NZ - New location established following purchase of Hawkins 2028 | H47: 8-10 Charlies Way | I47: Hamilton | J47: Waikato | K47: 3110 | L47: New Zealand | M47: Hamilton | N47: New Zealand | P47: Operational Control | Q47: Operational Control | R47: Transport & Infrastructure (T&I) | S47: Downer | T47: 100 | W47: Classification | X47: -37.800447 | Y47: 175.25785 | Z47: 301 | AA47: 42917
A48: Downer | B48: _CLOSED_BP_Central_Small Jobs | C48: Operations Center | D48: L9.DNZ.HC0330 | E48: 5257 | G48: Projects located at numerous sites throughout Central NZ - New location established following purchase of Hawkins 2017 | M48: Hamilton | N48: New Zealand | P48: Operational Control | Q48: Operational Control | R48: Transport & Infrastructure (T&I) | S48: Downer | T48: 100 | W48: Classification
A49: Downer | B49: _CLOSED_BP_South-Island_Christchurch Town Hall Con | C49: Other | D49: L9.DNZ.HS0120 | E49: 5229 | G49: Project Site - Building Construction - New location established following purchase of Hawkins 2061 - Christchurch City Council | H49: 86 Kilmore Street | I49: Christchurch | J49: Canterbury | K49: 8041 | L49: New Zealand | M49: Christchurch | N49: New Zealand | P49: Operational Control | Q49: Operational Control | R49: Transport & Infrastructure (T&I) | S49: Downer | T49: 100 | W49: Classification | X49: -43.526956 | Y49: 172.63483 | Z49: 302 | AA49: 42917
A50: Downer | B50: _CLOSED_BP_South-Island_RO-Addington | C50: Other | D50: L9.DNZ.SI | E50: 5226 | G50: Support services for projects located at numerous sites throughout South Island - New location established following purchase of Hawkins 2058 | H50: Unit 14 Barry Hogan Place | I50: Addington | J50: Canterbury | K50: 8011 | L50: New Zealand | M50: Christchurch | N50: New Zealand | P50: Operational Control | Q50: Operational Control | R50: Transport & Infrastructure (T&I) | S50: Downer | T50: 100 | W50: Classification | X50: -43.540693 | Y50: 172.59974 | Z50: 301 | AA50: 42917
A51: Downer | B51: _CLOSED_BP_South-Island_Small Jobs | C51: Operations Center | D51: L9.DNZ.HS0140 | E51: 5259 | G51: Projects located at numerous sites throughout South Island - New location established following purchase of Hawkins 2017 | M51: Canterbury | N51: New Zealand | P51: Operational Control | Q51: Operational Control | R51: Transport & Infrastructure (T&I) | S51: Downer | T51: 100 | W51: Classification
A52: Downer | B52: _CLOSED_BP_SubContractors | C52: Other | D52: L9.DNZ.COR | E52: 5320 | M52: Auckland | N52: New Zealand | P52: Operational Control | Q52: Operational Control | R52: Transport & Infrastructure (T&I) | S52: Downer | T52: 100 | W52: Classification
A53: Downer | B53: _CLOSED_BP_Wellington_NZ Post Podium Reinstatement | C53: Other | D53: L9.DNZ.HW0153 | E53: 5221 | G53: Project Site - Building Construction - New location established following purchase of Hawkins 2053 - NZ Post Properties | H53: 7 Waterloo Quay, Wellington CBD | I53: Wellington | J53: Wellington | K53: 6011 | L53: New Zealand | M53: Wellington | N53: New Zealand | P53: Operational Control | Q53: Operational Control | R53: Transport & Infrastructure (T&I) | S53: Downer | T53: 100 | W53: Classification | X53: -41.280732 | Y53: 174.77937 | Z53: 302 | AA53: 42917
A54: Downer | B54: _CLOSED_BP_Wellington_RO-Wellington | C54: Other | D54: L9.DNZ.WLG | E54: 5210 | G54: Support services for projects located at numerous sites throughout Wellington Region - New location established following purchase of Hawkins 2042 | H54: 265 Wakefield Street, CBD | I54: Wellington | J54: Wellington | K54: 6011 | L54: New Zealand | M54: Wellington | N54: New Zealand | P54: Operational Control | Q54: Operational Control | R54: Transport & Infrastructure (T&I) | S54: Downer | T54: 100 | W54: Classification | X54: -41.292407 | Y54: 174.78313 | Z54: 301 | AA54: 42917
A55: Downer | B55: _CLOSED_BP_Wellington_Small Jobs | C55: Operations Center | D55: L9.DNZ.COR | E55: 5258 | G55: Projects located at numerous sites throughout Welington - New location established following purchase of Hawkins 2017 | M55: Wellington | N55: New Zealand | P55: Operational Control | Q55: Operational Control | R55: Transport & Infrastructure (T&I) | S55: Downer | T55: 100 | W55: Classification
A56: Downer | B56: _CLOSED_Braiform Australia - Dandenong Warehouse ( | C56: Branch Office | D56: L9.S.18700011 | G56: No longer exists - 1 July 2009 | H56: 1/19 Commercial Drive | I56: Dandenong South | J56: VIC | K56: 3175 | M56: Victoria | N56: Australia | P56: Operational Control | Q56: Operational Control | R56: Corporate | S56: Downer | T56: 100 | W56: Classification | Z56: 696
A57: Downer | B57: _CLOSED_Brisbane - Roads | C57: Depot | D57: L9.J.170402 | E57: 8020 | F57: 8020 | G57: Lease commenced 5th October 2018. Office location is now under Qantas Dr. Location is closed. | H57: 60 - 62 Qantas Drive, Brisbane Airport | I57: Brisbane | J57: QLD | K57: 4008 | L57: Australia | M57: Brisbane | N57: Australia | P57: Operational Control | Q57: Operational Control | R57: Transport & Infrastructure (T&I) | S57: Downer | T57: 100 | W57: Classification | X57: -27.414474 | Y57: 153.09136 | Z57: 310 | AB57: 44377
A58: Downer | B58: _CLOSED_Broome | C58: Branch | D58: L9.J.17060521 | E58: 31 | H58: 3 Ward Street | I58: Broome | J58: Western Australia | K58: 6725 | L58: Australia | M58: Western Australia | N58: Australia | P58: Operational Control | Q58: Operational Control | R58: Transport & Infrastructure (T&I) | S58: Downer | T58: 100 | W58: Classification | X58: -17.988226 | Y58: 122.20207 | Z58: 310
A59: Downer | B59: _CLOSED_Camellia | C59: Depot | D59: L9.J.17010146 | E59: 36 | G59: RAP Processing | H59: 12 Grande Ave | I59: Camellia | J59: NSW | K59: 2142 | L59: Australia | M59: New South Wales | N59: Australia | P59: Operational Control | Q59: Operational Control | R59: Transport & Infrastructure (T&I) | S59: Downer | T59: 100 | W59: Classification | X59: -33.819 | Y59: 151.032 | Z59: 310
A60: Downer | B60: _CLOSED_Canningvale | C60: Other | D60: L9.J.706112 | E60: L9.J.706112 | F60: 40 | H60: 42 Magnet Rd | I60: Canning Vale | J60: Western Australia | K60: 6155 | L60: Australia | M60: Western Australia | N60: Australia | P60: Operational Control | Q60: Operational Control | R60: Rail & Transit Systems (RTS) | S60: Downer | T60: 100 | W60: Classification | X60: -32.061556 | Y60: 115.92772 | Z60: 239 | AA60: 40360 | AB60: 43281
A61: Downer | B61: _CLOSED_Charmhaven NSW | C61: Branch Office | D61: L9.S.14001229 | E61: 9046 | H61: Unit 5 132 Chelmsford Rd | I61: Charmhaven | J61: NSW | K61: 2263 | L61: Australia | M61: New South Wales | N61: Australia | P61: Operational Control | Q61: Operational Control | R61: Social Infra & Citizen Serv (SICS) | S61: Downer | T61: 100 | W61: Classification | X61: -33.238376 | Y61: 151.49433 | Z61: 692 | AB61: 45473
A62: Downer | B62: _CLOSED_Chinchilla Battery | C62: Construction Site | D62: L9.J.37740098 | E62: 1039 Banana Bridge Road, Brigalow | G62: Chinchilla Battery (BESS) | M62: Chinchilla | N62: Australia | P62: Operational Control | Q62: Operational Control | R62: Energy and Utilities (EU) | S62: Downer | T62: 100 | W62: Classification | AB62: 45632
A63: Downer | B63: _CLOSED_Collins Street - IPD | C63: Depot | D63: L9.J.200421 | E63: 6008 | H63: Collins St | I63: Melbourne | J63: VIC | K63: 3000 | M63: Victoria | N63: Australia | P63: Operational Control | Q63: Operational Control | R63: DT Infrastructure (pre Sept 23 divestment) | S63: Downer | T63: 100 | V63: 45199 | W63: Classification | X63: -37.818121 | Y63: 144.95728 | Z63: 692
A64: Downer | B64: _CLOSED_Comms - ACT | C64: Fleet Fuel | D64: L9.EMS.410.10277 | M64: Australian Capital Territory | N64: Australia | P64: Operational Control | Q64: Operational Control | R64: Energy and Utilities (EU) | S64: Downer | T64: 100 | W64: Classification | AB64: 44742
A65: Downer | B65: _CLOSED_Comms - HFC NSW | C65: Depot | D65: L9.J.234414 | E65: 7035 | H65: NSW | I65: NSW | M65: New South Wales | N65: Australia | P65: Operational Control | Q65: Operational Control | R65: Energy and Utilities (EU) | S65: Downer | T65: 100 | W65: Classification | Z65: 310 | AB65: 43921
A66: Downer | B66: _CLOSED_Comms - National Subcontractor | C66: Fleet Fuel | D66: L9.EMS.410.10280 | E66: 7014 | H66: T3, 39 Delhi Road | I66: North Ryde | J66: NSW | K66: 2113 | L66: Australia | M66: New South Wales | N66: Australia | P66: Operational Control | Q66: Operational Control | R66: Energy and Utilities (EU) | S66: Downer | T66: 100 | W66: Classification | X66: -33.823624 | Y66: 151.12254 | Z66: 310 | AB66: 45107
A67: Downer | B67: _CLOSED_Comms - NT | C67: Fleet Fuel | D67: L9.J.23440199 | M67: Northern Territory | N67: Australia | P67: Operational Control | Q67: Operational Control | R67: Energy and Utilities (EU) | S67: Downer | T67: 100 | W67: Classification | AB67: 44742
A68: Downer | B68: _CLOSED_Comms - QLD | C68: Plant | D68: L9.J.23420006 | E68: 7015 | H68: 2 Burke Street | I68: Woolloongabba | J68: QLD | K68: 4102 | L68: Australia | M68: Queensland | N68: Australia | P68: Operational Control | Q68: Operational Control | R68: Energy and Utilities (EU) | S68: Downer | T68: 100 | W68: Classification | X68: -27.495134 | Y68: 153.03398 | Z68: 310 | AB68: 44742
A69: Downer | B69: _CLOSED_Comms - SA | C69: Plant | D69: L9.EMS.410.10245 | E69: 7025 | H69: Linden Lane | I69: Regency Park | J69: SA | K69: 5065 | L69: Australia | M69: South Australia | N69: Australia | P69: Operational Control | Q69: Operational Control | R69: Energy and Utilities (EU) | S69: Downer | T69: 100 | W69: Classification | X69: -34.85969 | Y69: 138.57241 | Z69: 310 | AB69: 44926
A70: Downer | B70: _CLOSED_Comms - TAS | C70: Fleet Fuel | D70: L9.J.23440247 | M70: Tasmania | N70: Australia | P70: Operational Control | Q70: Operational Control | R70: Energy and Utilities (EU) | S70: Downer | T70: 100 | W70: Classification | AB70: 44742
A71: Downer | B71: _CLOSED_Comms - VIC | C71: Plant | D71: L9.J.23440042 | E71: 7016 | H71: 567 Collins Street | I71: Melbourne | J71: VIC | K71: 3000 | L71: Australia | M71: Victoria | N71: Australia | P71: Operational Control | Q71: Operational Control | R71: Energy and Utilities (EU) | S71: Downer | T71: 100 | W71: Classification | X71: -37.819015 | Y71: 144.95576 | Z71: 310 | AB71: 44742
A72: Downer | B72: _CLOSED_Comms - WA | C72: Plant | D72: L9.J.23440194 | E72: 7026 | H72: 9 Modal Crescent | I72: Canning Vale | J72: WA | K72: 6155 | L72: Australia | M72: Western Australia | N72: Australia | P72: Operational Control | Q72: Operational Control | R72: Energy and Utilities (EU) | S72: Downer | T72: 100 | W72: Classification | X72: -32.071836 | Y72: 115.91159 | Z72: 310 | AB72: 44742
A73: Downer | B73: _CLOSED_Copping Landfill | C73: Aerobic Treatment - Managed | D73: L9.J.17030214 | M73: Tasmania | N73: Australia | P73: Operational Control | Q73: Operational Control | R73: Transport & Infrastructure (T&I) | S73: Downer | T73: 100 | W73: Classification | AB73: 45473
A74: Downer | B74: _CLOSED_Corporate - 549 St Kilda Rd (Melbourne VIC) | C74: Head Office | D74: L9.COR.130.02109 | E74: 9029 | H74: 549 St Kilda Rd | I74: Melbourne | J74: VIC | K74: 3004 | M74: Victoria | N74: Australia | P74: Operational Control | Q74: Operational Control | R74: Corporate | S74: Downer | T74: 100 | W74: Classification | X74: -37.846581 | Y74: 144.97996 | Z74: 729 | AB74: 45596
A75: Downer | B75: _CLOSED_Corporate - Offices (Fortitude Valley QLD) | C75: Branch Office | D75: L9.WAU.000886 | E75: L9.WAU.000886 | H75: 15 James St | I75: Fortitude Valley | J75: QLD | K75: 4006 | M75: Queensland | N75: Australia | P75: Operational Control | Q75: Operational Control | R75: Corporate | S75: Downer | T75: 100 | W75: Classification | X75: -27.456262 | Y75: 153.03892 | Z75: 696
A76: Downer | B76: _CLOSED_Corporate - Offices (Kewdale WA) | C76: Branch Office | D76: L9.S.11000860 | E76: 9028 | H76: 491 Abernathy Road | I76: Kewdale | J76: WA | K76: 6105 | M76: Western Australia | N76: Australia | P76: Operational Control | Q76: Operational Control | R76: Corporate | S76: Downer | T76: 100 | W76: Classification | X76: -31.973944 | Y76: 115.95056 | Z76: 729
A77: Downer | B77: _CLOSED_Corporate - Offices (Moonah TAS) | C77: Branch Office | D77: L9.S.S859 | E77: 9030 | G77: Closed on 09/2020 | H77: Level 1 134-136 Main Rd | I77: Moonah | J77: TAS | K77: 7009 | M77: Tasmania | N77: Australia | P77: Operational Control | Q77: Operational Control | R77: Corporate | S77: Downer | T77: 100 | W77: Classification | X77: -42.845115 | Y77: 147.29313 | Z77: 729 | AB77: 44075
A78: Downer | B78: _CLOSED_Corporate - Offices (Newcastle NSW) | C78: Branch Office | D78: L9.S.11000810 | E78: 9023 | G78: This location is merged to CS-Cardiff. All electricity/Water/Gas accounts are moved to CS-Cardiff | H78: Unit 3a 88 Munibung Road | I78: Cardiff | J78: NSW | K78: 2285 | M78: New South Wales | N78: Australia | P78: Operational Control | Q78: Operational Control | R78: Corporate | S78: Downer | T78: 100 | W78: Classification | X78: -32.943042 | Y78: 151.63911 | Z78: 696 | AB78: 41783
A79: Downer | B79: _CLOSED_Corporate - Offices (Sydney Rhodes NSW) | C79: Branch Office | D79: L9.WAU.000887 | E79: L9.WAU.000887 | H79: Level 4 4/5 Rider Boulevard | I79: Rhodes | J79: NSW | K79: 2138 | L79: Australia | M79: New South Wales | N79: Australia | P79: Operational Control | Q79: Operational Control | R79: Corporate | S79: Downer | T79: 100 | W79: Classification | X79: -33.832374 | Y79: 151.08616 | Z79: 729 | AB79: 44943
A80: Downer | B80: _CLOSED_Corporate Offices - (Rhodes NSW) | C80: Branch Office | D80: L9.WAU.003012 | E80: L9.WAU.003012 | H80: 4 Marquet Street | I80: Rhodes | J80: NSW | K80: 2138 | M80: New South Wales | N80: Australia | P80: Operational Control | Q80: Operational Control | R80: Corporate | S80: Downer | T80: 100 | W80: Classification
A81: Downer | B81: _CLOSED_CS - Cardiff Office | C81: Branch Office | D81: L9.S.11000101 | H81: Unit 3a Warehouse/Office, 88 Munibung Rd, | I81: CARDIFF | J81: NSW | K81: 2285 | M81: New South Wales | N81: Australia | P81: Operational Control | Q81: Operational Control | R81: Social Infra & Citizen Serv (SICS) | S81: Downer | T81: 100 | W81: Classification | Z81: 696
A82: Downer | B82: _CLOSED_CS - Nerang Office (QLD) | C82: Branch Office | D82: L9.S.16001990 | H82: Unit 7 17 Indy Crt | I82: Nerang | J82: QLD | K82: 4211 | M82: Queensland | N82: Australia | P82: Operational Control | Q82: Operational Control | R82: Social Infra & Citizen Serv (SICS) | S82: Downer | T82: 100 | W82: Classification | Z82: 696
A83: Downer | B83: _CLOSED_CS - Old Rockhampton Office (QLD) | C83: Branch Office | D83: L9.S.16008157 | H83: 32 Denham St | I83: Rockhampton | J83: QLD | K83: 4700 | M83: Queensland | N83: Australia | P83: Operational Control | Q83: Operational Control | R83: Social Infra & Citizen Serv (SICS) | S83: Downer | T83: 100 | W83: Classification | Z83: 696
A84: Downer | B84: _CLOSED_CS - Osborne Park Office (WA) | C84: Branch Office | D84: L9.S.11000865 | G84: 31 January 2013 - exited and now under sublease. | H84: 43 Edward Street | I84: Osborne Park | J84: WA | K84: 6017 | M84: Western Australia | N84: Australia | P84: Operational Control | Q84: Operational Control | R84: Social Infra & Citizen Serv (SICS) | S84: Downer | T84: 100 | W84: Classification | Z84: 696
A85: Downer | B85: _CLOSED_Darwin - Bombing Rd, Winnellie | C85: Other | D85: L9.S.16013419 | E85: 7040 | G85: Skilltech in Bombing Road, Winnellie until Oct-19 and then moved to 23a/90 Frances Bay Drv, Stuart Park, NT 0820. Closed in Jan 2021 | H85: 23a 90 Frances Bay Drive | I85: Stuart Park | J85: Northern Territory | K85: 0820 | L85: Australia | M85: Northern Territory | N85: Australia | P85: Operational Control | Q85: Operational Control | R85: Energy and Utilities (EU) | S85: Downer | T85: 100 | W85: Classification | X85: -12.42799 | Y85: 130.88035 | Z85: 692 | AB85: 44197
A86: Downer | B86: _CLOSED_DEF Fleet ACT | C86: Fleet Fuel | D86: L9.S.14000508 | E86: 9169 | G86: Leaseplan vehicles transitioned through to FTC data at end of FY23. | M86: Australian Capital Territory | N86: Australia | P86: Operational Control | Q86: Operational Control | R86: Social Infra & Citizen Serv (SICS) | S86: Downer | T86: 100 | W86: Classification
A87: Downer | B87: _CLOSED_DEF Fleet NSW | C87: Fleet Fuel | D87: L9.S.14000514 | E87: 9168 | G87: Leaseplan vehicles transitioned through to FTC data at end of FY23. | M87: New South Wales | N87: Australia | P87: Operational Control | Q87: Operational Control | R87: Social Infra & Citizen Serv (SICS) | S87: Downer | T87: 100 | W87: Classification
A88: Downer | B88: _CLOSED_DEF Fleet NT | C88: Fleet Fuel | D88: L9.S.14000479 | E88: 9207 | G88: Leaseplan vehicles transitioned through to FTC data at end of FY23. | M88: Northern Territory | N88: Australia | P88: Operational Control | Q88: Operational Control | R88: Social Infra & Citizen Serv (SICS) | S88: Downer | T88: 100 | W88: Classification
A89: Downer | B89: _CLOSED_DEF Fleet QLD | C89: Fleet Fuel | D89: L9.S.14000494 | E89: 9170 | G89: Leaseplan vehicles transitioned through to FTC data at end of FY23. | M89: Queensland | N89: Australia | P89: Operational Control | Q89: Operational Control | R89: Social Infra & Citizen Serv (SICS) | S89: Downer | T89: 100 | W89: Classification
A90: Downer | B90: _CLOSED_DEF Fleet SA | C90: Fleet Fuel | D90: L9.S.14000487 | E90: 9208 | G90: Leaseplan vehicles transitioned through to FTC data at end of FY23. | M90: South Australia | N90: Australia | P90: Operational Control | Q90: Operational Control | R90: Social Infra & Citizen Serv (SICS) | S90: Downer | T90: 100 | W90: Classification
A91: Downer | B91: _CLOSED_DEF Fleet VIC | C91: Fleet Fuel | D91: L9.S.16015942 | E91: 9171 | G91: Leaseplan vehicles transitioned through to FTC data at end of FY23. | M91: Victoria | N91: Australia | P91: Operational Control | Q91: Operational Control | R91: Social Infra & Citizen Serv (SICS) | S91: Downer | T91: 100 | W91: Classification
A92: Downer | B92: _CLOSED_DEF Fleet WA | C92: Fleet Fuel | D92: L9.S.14000476 | E92: 9214 | G92: Leaseplan vehicles transitioned through to FTC data at end of FY23. | M92: Western Australia | N92: Australia | P92: Operational Control | Q92: Operational Control | R92: Social Infra & Citizen Serv (SICS) | S92: Downer | T92: 100 | W92: Classification
A93: Downer | B93: _CLOSED_Denny Avenue, Metronet | C93: Construction Site | D93: L9.J.20044061 | M93: Kelmscott | N93: Australia | P93: Operational Control | Q93: Operational Control | R93: DT Infrastructure (pre Sept 23 divestment) | S93: Downer | T93: 100 | V93: 45199 | W93: Classification
A94: Downer | B94: _CLOSED_Depot_BP_Auckland_Plant-Yard | C94: Other | D94: L9.DNZ.PLT | E94: 5186 | G94: Construction equipment plant yard storage and distribution - New location established following purchase of Hawkins 2018 | H94: 1-3 Ash Road, Wiri | I94: Auckland | J94: Auckland | K94: 2022 | L94: New Zealand | M94: Manurewa | N94: New Zealand | P94: Operational Control | Q94: Operational Control | R94: Transport & Infrastructure (T&I) | S94: Downer | T94: 100 | W94: Classification | X94: -37.002534 | Y94: 174.86511 | Z94: 663 | AA94: 42917
A95: Downer | B95: _CLOSED_Depot_T_Balclutha | C95: Other | D95: L9.DNZJ.55674 | E95: 5022 | G95: Support Services for TS - New facilities established for more granular reporting and to reflect new structure for FY17. See facility named "NZ-Infrastructure Services" for historical data. | H95: 11 Athol Place | I95: Balclutha | J95: Otago | K95: 8051 | L95: New Zealand | M95: Balclutha | N95: New Zealand | P95: Operational Control | Q95: Operational Control | R95: Transport & Infrastructure (T&I) | S95: Downer | T95: 100 | U95: 1899/12/31 | W95: Classification | X95: -46.232926 | Y95: 169.75259 | Z95: 729 | AA95: 42917
A96: Downer | B96: _CLOSED_Depot_T_Blenheim | C96: Other | D96: L9.DNZJ.55612 | E96: 5023 | G96: Support Services for TS - New facilities established for more granular reporting and to reflect new structure for FY17. See facility named "NZ-Infrastructure Services" for historical data. | H96: 7 Freswick Street | I96: Blenheim | J96: Marlborough | K96: 7391 | L96: New Zealand | M96: Blenheim | N96: New Zealand | P96: Operational Control | Q96: Operational Control | R96: Transport & Infrastructure (T&I) | S96: Downer | T96: 100 | U96: 1899/12/31 | W96: Classification | X96: -41.514532 | Y96: 173.96193 | Z96: 729 | AA96: 42917
A97: Downer | B97: _CLOSED_Depot_T_Christchurch (McLeans Is) | C97: Other | D97: L9.DNZJ.55650 | E97: 5024 | G97: Support Services for TS - New facilities established for more granular reporting and to reflect new structure for FY17. See facility named "NZ-Infrastructure Services" for historical data. | H97: 397 Mcleans Island Road, Harewood | I97: Christchurch | J97: Canterbury | K97: 9018 | L97: New Zealand | M97: Christchurch | N97: New Zealand | P97: Operational Control | Q97: Operational Control | R97: Transport & Infrastructure (T&I) | S97: Downer | T97: 100 | U97: 1899/12/31 | W97: Classification | X97: -43.476427 | Y97: 172.51673 | Z97: 729 | AA97: 42917
A98: Downer | B98: _CLOSED_Depot_T_Cromwell | C98: Other | D98: L9.DNZJ.55686 | E98: 5028 | G98: Support Services for TS - New facilities established for more granular reporting and to reflect new structure for FY17. See facility named "NZ-Infrastructure Services" for historical data. | H98: 922 Luggate-Cromwell Road | I98: Mount Pisa | J98: Otago | K98: 9710 | L98: New Zealand | M98: Clyde | N98: New Zealand | P98: Operational Control | Q98: Operational Control | R98: Transport & Infrastructure (T&I) | S98: Downer | T98: 100 | U98: 1899/12/31 | W98: Classification | X98: -44.962849 | Y98: 169.24514 | Z98: 729 | AA98: 42917
A99: Downer | B99: _CLOSED_Depot_T_Culverden (Excell) | C99: Other | D99: L9.DNZJ.553801 | E99: L9.DNZJ.553801 | G99: Support Services for TS - New facilities established for more granular reporting and to reflect new structure for FY17. See facility named "NZ-Infrastructure Services" for historical data. | H99: 26 Lyndon Street | I99: Culverdon | J99: Canterbury | K99: 7392 | L99: New Zealand | M99: Christchurch | N99: New Zealand | P99: Operational Control | Q99: Operational Control | R99: Transport & Infrastructure (T&I) | S99: Downer | T99: 100 | U99: 1899/12/31 | W99: Classification | X99: -43.535876 | Y99: 172.60216 | Z99: 729 | AA99: 42917
A100: Downer | B100: _CLOSED_Depot_T_Dargaville | C100: Depot | D100: L9.DNZJ.55908 | E100: 5252 | M100: Northland | N100: New Zealand | P100: Operational Control | Q100: Operational Control | R100: Transport & Infrastructure (T&I) | S100: Downer | T100: 100 | U100: 1899/12/31 | W100: Classification
...

Sheet Extract for Accounts 1 Oct 25
A1: Location Link | B1: Account Link | C1: Associate | D1: Location | E1: Location Account Ref | F1: Data Type | G1: Account Style | H1: Sub Type | I1: Supplier | J1: Account Number | K1: Account Reference | L1: Reader | M1: Serial_No | N1: Opened On | O1: Replaced On | P1: Usage Type | Q1: Use | R1: Apportionment | S1: Effective From | T1: Effective To | U1: Cost Centre Group Chain | V1: Cost Centre | W1: Report Percent | X1: Cost Centre Effective From | Y1: Cost Centre Effective To | Z1: Cost Centre Membership Description | AA1: Relationship | AB1: Related Account | AC1: Relationship Percent | AD1: Relationship Effective From | AE1: Relationship Effective To | AF1: Account Style Accrue Type | AG1: Account Style Consumption Accrue Method | AH1: Account Style Cost Accrue Method | AI1: Updated On
A2: 6044548 | B2: 6325209 | C2: Downer | D2: REV_Asset & Development Services | E2: ADS3197S | F2: Revenue [AUD Million] | G2: Revenue - AUD Million | I2: Downer | J2: FY25REV_Asset & Development Services | K2: REV_Asset & Development Services | L2: Revenue | AF2: Contiguous Data | AG2: Inherit Associate Settings | AH2: Inherit Associate Settings | AI2: 45735.809
A3: 6044557 | B3: 6325210 | C3: Downer | D3: REV_Base & Estate Management | E3: SICSBEM | F3: Revenue [AUD Million] | G3: Revenue - AUD Million | I3: Downer | J3: FY25REV_Base & Estate Management | K3: REV_Base & Estate Management | L3: Revenue | AF3: Contiguous Data | AG3: Inherit Associate Settings | AH3: Inherit Associate Settings | AI3: 45735.809
A4: 6044537 | B4: 6325211 | C4: Downer | D4: REV_Corporate Australia | E4: CORAU | F4: Revenue [AUD Million] | G4: Revenue - AUD Million | I4: Downer | J4: FY25REV_Corporate Australia | K4: REV_Corporate Australia | L4: Revenue | AF4: Contiguous Data | AG4: Inherit Associate Settings | AH4: Inherit Associate Settings | AI4: 45735.809
A5: 6044561 | B5: 6325212 | C5: Downer | D5: REV_Downer Professional Services | E5: SICSDPS | F5: Revenue [AUD Million] | G5: Revenue - AUD Million | I5: Downer | J5: FY25REV_Downer Professional Services | K5: REV_Downer Professional Services | L5: Revenue | AF5: Contiguous Data | AG5: Inherit Associate Settings | AH5: Inherit Associate Settings | AI5: 45735.809
A6: 6046098 | B6: 6325213 | C6: Downer | D6: REV_E&C Legacy | E6: L9.J.362020 | F6: Revenue [AUD Million] | G6: Revenue - AUD Million | I6: Downer | J6: FY25REV_E&C Legacy | K6: REV_E&C Legacy | L6: Revenue | AF6: Contiguous Data | AG6: Inherit Associate Settings | AH6: Inherit Associate Settings | AI6: 45735.809
A7: 6046337 | B7: 6325214 | C7: Downer | D7: REV_EU Gap | E7: L9.J.392150 | F7: Revenue [AUD Million] | G7: Revenue - AUD Million | I7: Downer | J7: FY25REV_EU Gap | K7: REV_EU Gap | L7: Revenue | AF7: Contiguous Data | AG7: Inherit Associate Settings | AH7: Inherit Associate Settings | AI7: 45735.809
A8: 6046339 | B8: 6325215 | C8: Downer | D8: REV_EU Support | E8: L9.DUA.30172800 | F8: Revenue [AUD Million] | G8: Revenue - AUD Million | I8: Downer | J8: FY25REV_EU Support | K8: REV_EU Support | L8: Revenue | AF8: Contiguous Data | AG8: Inherit Associate Settings | AH8: Inherit Associate Settings | AI8: 45735.809
A9: 6046332 | B9: 6325216 | C9: Downer | D9: REV_Fleet & Assets | E9: L9.DNZJ.1937 | F9: Revenue [AUD Million] | G9: Revenue - AUD Million | I9: Downer | J9: FY25REV_Fleet & Assets | K9: REV_Fleet & Assets | L9: Revenue | AF9: Contiguous Data | AG9: Inherit Associate Settings | AH9: Inherit Associate Settings | AI9: 45735.809
A10: 6044562 | B10: 6325217 | C10: Downer | D10: REV_Government & IFM | E10: SICSGIFM | F10: Revenue [AUD Million] | G10: Revenue - AUD Million | I10: Downer | J10: FY25REV_Government & IFM | K10: REV_Government & IFM | L10: Revenue | AF10: Contiguous Data | AG10: Inherit Associate Settings | AH10: Inherit Associate Settings | AI10: 45735.809
A11: 6044532 | B11: 6325218 | C11: Downer | D11: REV_Hawkins | E11: TIHA | F11: Revenue [AUD Million] | G11: Revenue - AUD Million | I11: Downer | J11: FY25REV_Hawkins | K11: REV_Hawkins | L11: Revenue | AF11: Contiguous Data | AG11: Inherit Associate Settings | AH11: Inherit Associate Settings | AI11: 45735.809
A12: 6044560 | B12: 6325219 | C12: Downer | D12: REV_Health & Education | E12: SICSHE | F12: Revenue [AUD Million] | G12: Revenue - AUD Million | I12: Downer | J12: FY25REV_Health & Education | K12: REV_Health & Education | L12: Revenue | AF12: Contiguous Data | AG12: Inherit Associate Settings | AH12: Inherit Associate Settings | AI12: 45735.809
A13: 6046338 | B13: 6325220 | C13: Downer | D13: REV_Industrial & Power Generation | E13: L9.ENG.360.84.105 | F13: Revenue [AUD Million] | G13: Revenue - AUD Million | I13: Downer | J13: FY25REV_Industrial & Power Generation | K13: REV_Industrial & Power Generation | L13: Revenue | AF13: Contiguous Data | AG13: Inherit Associate Settings | AH13: Inherit Associate Settings | AI13: 45735.809
... A35: 6046336 | B35: 6325242 | C35: Downer | D35: REV_Water | E35: L9.J.39220126 | F35: Revenue [AUD Million] | G35: Revenue - AUD Million | I35: Downer | J35: FY25REV_Water | K35: REV_Water | L35: Revenue | AF35: Contiguous Data | AG35: Inherit Associate Settings | AH35: Inherit Associate Settings | AI35: 45735.809
A36: 6044550 | B36: 6222427 | C36: Downer | D36: REV_Rail Services Victoria Pty Ltd | E36: RTSRSV | F36: Revenue [AUD Million] | G36: Revenue - AUD Million | I36: Downer | J36: REV_Rail Services Victoria Pty Ltd | L36: Multi Template | P36: Decarbonisation Pathway | Q36: Other | R36: 100 | AF36: Contiguous Data | AG36: Inherit Associate Settings | AH36: Inherit Associate Settings | AI36: 45831.728

Sheet Feb Check - By Line Item
A1: Feb 2026 Revenue — Account Setup Verification by Line Item
A2: Generated: 23 Apr 2026 | FY26 Revenue source vs Account_Setup_and_Data_Load Mar rows
A3: Record Reference | B3: Location | C3: FY26 Revenue (Feb) | D3: Account Setup (Feb) | E3: Difference | F3: Status
A4: T&I NZ North | B4: REV_Transport & Infrastructure NZ | C4: =IFERROR(INDEX('FY26 Revenue'!L:L,MATCH(A4,'FY26 Revenue'!C:C,0)),IFERROR(INDEX('FY26 Revenue'!L:L,MATCH(A4,'FY26 Revenue'!B:B,0)),0)) -> 53.1 | D4: =SUMIFS(Account_Setup_and_Data_Load!T:T,Account_Setup_and_Data_Load!L:L,DATE(2026,3,1),Account_Setup_and_Data_Load!R:R,A4) -> 53.1 | E4: =ROUND(D4-C4,4) -> 0 | F4: =IF(ABS(E4)<=0.001,"OK","MISMATCH") -> OK
A5: T&I NZ South | B5: REV_Transport & Infrastructure NZ | C5: =IFERROR(INDEX('FY26 Revenue'!L:L,MATCH(A5,'FY26 Revenue'!C:C,0)),IFERROR(INDEX('FY26 Revenue'!L:L,MATCH(A5,'FY26 Revenue'!B:B,0)),0)) -> 54.8 | D5: =SUMIFS(Account_Setup_and_Data_Load!T:T,Account_Setup_and_Data_Load!L:L,DATE(2026,3,1),Account_Setup_and_Data_Load!R:R,A5) -> 54.8 | E5: =ROUND(D5-C5,4) -> 0 | F5: =IF(ABS(E5)<=0.001,"OK","MISMATCH") -> OK
A6: T&I NZ Infrastructure Delivery | B6: REV_Transport & Infrastructure NZ | C6: =IFERROR(INDEX('FY26 Revenue'!L:L,MATCH(A6,'FY26 Revenue'!C:C,0)),IFERROR(INDEX('FY26 Revenue'!L:L,MATCH(A6,'FY26 Revenue'!B:B,0)),0)) -> 30.6 | D6: =SUMIFS(Account_Setup_and_Data_Load!T:T,Account_Setup_and_Data_Load!L:L,DATE(2026,3,1),Account_Setup_and_Data_Load!R:R,A6) -> 30.6 | E6: =ROUND(D6-C6,4) -> 0 | F6: =IF(ABS(E6)<=0.001,"OK","MISMATCH") -> OK
A7: T&I NZ Hawkins | B7: REV_Transport & Infrastructure NZ | C7: =IFERROR(INDEX('FY26 Revenue'!L:L,MATCH(A7,'FY26 Revenue'!C:C,0)),IFERROR(INDEX('FY26 Revenue'!L:L,MATCH(A7,'FY26 Revenue'!B:B,0)),0)) -> 54.5 | D7: =SUMIFS(Account_Setup_and_Data_Load!T:T,Account_Setup_and_Data_Load!L:L,DATE(2026,3,1),Account_Setup_and_Data_Load!R:R,A7) -> 54.5 | E7: =ROUND(D7-C7,4) -> 0 | F7: =IF(ABS(E7)<=0.001,"OK","MISMATCH") -> OK
A8: T&I NZ National Operations | B8: REV_Transport & Infrastructure NZ | C8: =IFERROR(INDEX('FY26 Revenue'!L:L,MATCH(A8,'FY26 Revenue'!C:C,0)),IFERROR(INDEX('FY26 Revenue'!L:L,MATCH(A8,'FY26 Revenue'!B:B,0)),0)) -> 15.7 | D8: =SUMIFS(Account_Setup_and_Data_Load!T:T,Account_Setup_and_Data_Load!L:L,DATE(2026,3,1),Account_Setup_and_Data_Load!R:R,A8) -> 15.7 | E8: =ROUND(D8-C8,4) -> 0 | F8: =IF(ABS(E8)<=0.001,"OK","MISMATCH") -> OK
A9: T&I NZ Overheads | B9: REV_Transport & Infrastructure NZ | C9: =IFERROR(INDEX('FY26 Revenue'!L:L,MATCH(A9,'FY26 Revenue'!C:C,0)),IFERROR(INDEX('FY26 Revenue'!L:L,MATCH(A9,'FY26 Revenue'!B:B,0)),0)) -> 0.3 | D9: =SUMIFS(Account_Setup_and_Data_Load!T:T,Account_Setup_and_Data_Load!L:L,DATE(2026,3,1),Account_Setup_and_Data_Load!R:R,A9) -> 0.3 | E9: =ROUND(D9-C9,4) -> 0 | F9: =IF(ABS(E9)<=0.001,"OK","MISMATCH") -> OK
A10: T&I AU Asphalt & Products | B10: REV_Transport & Infrastructure NZ | C10: =IFERROR(INDEX('FY26 Revenue'!L:L,MATCH(A10,'FY26 Revenue'!C:C,0)),IFERROR(INDEX('FY26 Revenue'!L:L,MATCH(A10,'FY26 Revenue'!B:B,0)),0)) -> 70.3 | D10: =SUMIFS(Account_Setup_and_Data_Load!T:T,Account_Setup_and_Data_Load!L:L,DATE(2026,3,1),Account_Setup_and_Data_Load!R:R,A10) -> 70.3 | E10: =ROUND(D10-C10,4) -> 0 | F10: =IF(ABS(E10)<=0.001,"OK","MISMATCH") -> OK
A11: Maintenance & ITS | B11: REV_Transport & Infrastructure AU | C11: =IFERROR(INDEX('FY26 Revenue'!L:L,MATCH(A11,'FY26 Revenue'!C:C,0)),IFERROR(INDEX('FY26 Revenue'!L:L,MATCH(A11,'FY26 Revenue'!B:B,0)),0)) -> 38.5 | D11: =SUMIFS(Account_Setup_and_Data_Load!T:T,Account_Setup_and_Data_Load!L:L,DATE(2026,3,1),Account_Setup_and_Data_Load!R:R,A11) -> 38.5 | E11: =ROUND(D11-C11,4) -> 0 | F11: =IF(ABS(E11)<=0.001,"OK","MISMATCH") -> OK
A12: Pavement Rehabilitation & Civils | B12: REV_Transport & Infrastructure AU | C12: =IFERROR(INDEX('FY26 Revenue'!L:L,MATCH(A12,'FY26 Revenue'!C:C,0)),IFERROR(INDEX('FY26 Revenue'!L:L,MATCH(A12,'FY26 Revenue'!B:B,0)),0)) -> 9.3 | D12: =SUMIFS(Account_Setup_and_Data_Load!T:T,Account_Setup_and_Data_Load!L:L,DATE(2026,3,1),Account_Setup_and_Data_Load!R:R,A12) -> 9.3 | E12: =ROUND(D12-C12,4) -> 0 | F12: =IF(ABS(E12)<=0.001,"OK","MISMATCH") -> OK
A13: Specialised Pavements & Projects | B13: REV_Transport & Infrastructure AU | C13: =IFERROR(INDEX('FY26 Revenue'!L:L,MATCH(A13,'FY26 Revenue'!C:C,0)),IFERROR(INDEX('FY26 Revenue'!L:L,MATCH(A13,'FY26 Revenue'!B:B,0)),0)) -> 3.7 | D13: =SUMIFS(Account_Setup_and_Data_Load!T:T,Account_Setup_and_Data_Load!L:L,DATE(2026,3,1),Account_Setup_and_Data_Load!R:R,A13) -> 3.7 | E13: =ROUND(D13-C13,4) -> 0 | F13: =IF(ABS(E13)<=0.001,"OK","MISMATCH") -> OK
A14: Thin Surfacing | B14: REV_Transport & Infrastructure AU | C14: =IFERROR(INDEX('FY26 Revenue'!L:L,MATCH(A14,'FY26 Revenue'!C:C,0)),IFERROR(INDEX('FY26 Revenue'!L:L,MATCH(A14,'FY26 Revenue'!B:B,0)),0)) -> 37.2 | D14: =SUMIFS(Account_Setup_and_Data_Load!T:T,Account_Setup_and_Data_Load!L:L,DATE(2026,3,1),Account_Setup_and_Data_Load!R:R,A14) -> 37.2 | E14: =ROUND(D14-C14,4) -> 0 | F14: =IF(ABS(E14)<=0.001,"OK","MISMATCH") -> OK
A15: BIA | B15: REV_Transport & Infrastructure AU | C15: =IFERROR(INDEX('FY26 Revenue'!L:L,MATCH(A15,'FY26 Revenue'!C:C,0)),IFERROR(INDEX('FY26 Revenue'!L:L,MATCH(A15,'FY26 Revenue'!B:B,0)),0)) -> 5.8 | D15: =SUMIFS(Account_Setup_and_Data_Load!T:T,Account_Setup_and_Data_Load!L:L,DATE(2026,3,1),Account_Setup_and_Data_Load!R:R,A15) -> 5.8 | E15: =ROUND(D15-C15,4) -> 0 | F15: =IF(ABS(E15)<=0.001,"OK","MISMATCH") -> OK
... A82: Intra Elim | B82: REV_Intra Elim | C82: =IFERROR(INDEX('FY26 Revenue'!L:L,MATCH(A82,'FY26 Revenue'!C:C,0)),IFERROR(INDEX('FY26 Revenue'!L:L,MATCH(A82,'FY26 Revenue'!B:B,0)),0)) -> 0.1 | D82: =SUMIFS(Account_Setup_and_Data_Load!T:T,Account_Setup_and_Data_Load!L:L,DATE(2026,3,1),Account_Setup_and_Data_Load!R:R,A82) -> 0.1 | E82: =ROUND(D82-C82,4) -> 0 | F82: =IF(ABS(E82)<=0.001,"OK","MISMATCH") -> OK
A83: TOTALS | C83: =SUM(C4:C82) -> 845.8 | D83: =SUM(D4:D82) -> 845.8 | E83: =ROUND(D83-C83,4) -> 0 | F83: =COUNTIF(F4:F82,"OK")&"/"&COUNTA(F4:F82)&" OK"&IF(COUNTIF(F4:F82,"MISMATCH")>0," — "&COUNTIF(F4:F82,"MISMATCH")&" MISMATCH","") -> 79/79 OK

Sheet Monthly Totals Check
A1: FY26 Revenue — Monthly Totals: FY26 Revenue Sheet vs Account Setup
A2: Generated: 23 Apr 2026
A3: Month | B3: FY26 Revenue Sheet Total | C3: Account Setup Total | D3: Difference | E3: Row Count (Setup) | F3: Status
A4: Jul 25 | B4: =SUM('FY26 Revenue'!D2:D80) -> 780.7 | C4: =SUMIFS(Account_Setup_and_Data_Load!T:T,Account_Setup_and_Data_Load!L:L,DATE(2025,7,1)) -> 780.7 | D4: =ROUND(C4-B4,2) -> 0 | E4: =COUNTIF(Account_Setup_and_Data_Load!L:L,DATE(2025,7,1)) -> 79 | F4: =IF(ABS(D4)<=0.15,"OK","MISMATCH") -> OK
A5: Aug 25 | B5: =SUM('FY26 Revenue'!E2:E80) -> 751.7 | C5: =SUMIFS(Account_Setup_and_Data_Load!T:T,Account_Setup_and_Data_Load!L:L,DATE(2025,8,1)) -> 751.7 | D5: =ROUND(C5-B5,2) -> 0 | E5: =COUNTIF(Account_Setup_and_Data_Load!L:L,DATE(2025,8,1)) -> 79 | F5: =IF(ABS(D5)<=0.15,"OK","MISMATCH") -> OK
A6: Sep 25 | B6: =SUM('FY26 Revenue'!F2:F80) -> 831.2 | C6: =SUMIFS(Account_Setup_and_Data_Load!T:T,Account_Setup_and_Data_Load!L:L,DATE(2025,9,1)) -> 831.2 | D6: =ROUND(C6-B6,2) -> 0 | E6: =COUNTIF(Account_Setup_and_Data_Load!L:L,DATE(2025,9,1)) -> 79 | F6: =IF(ABS(D6)<=0.15,"OK","MISMATCH") -> OK
A7: Oct 25 | B7: =SUM('FY26 Revenue'!G2:G80) -> 882.3 | C7: =SUMIFS(Account_Setup_and_Data_Load!T:T,Account_Setup_and_Data_Load!L:L,DATE(2025,10,1)) -> 882.3 | D7: =ROUND(C7-B7,2) -> 0 | E7: =COUNTIF(Account_Setup_and_Data_Load!L:L,DATE(2025,10,1)) -> 79 | F7: =IF(ABS(D7)<=0.15,"OK","MISMATCH") -> OK
A8: Nov 25 | B8: =SUM('FY26 Revenue'!H2:H80) -> 879.6 | C8: =SUMIFS(Account_Setup_and_Data_Load!T:T,Account_Setup_and_Data_Load!L:L,DATE(2025,11,1)) -> 879.6 | D8: =ROUND(C8-B8,2) -> 0 | E8: =COUNTIF(Account_Setup_and_Data_Load!L:L,DATE(2025,11,1)) -> 79 | F8: =IF(ABS(D8)<=0.15,"OK","MISMATCH") -> OK
A9: Dec 25 | B9: =SUM('FY26 Revenue'!I2:I80) -> 793.2 | C9: =SUMIFS(Account_Setup_and_Data_Load!T:T,Account_Setup_and_Data_Load!L:L,DATE(2025,12,1)) -> 793.2 | D9: =ROUND(C9-B9,2) -> 0 | E9: =COUNTIF(Account_Setup_and_Data_Load!L:L,DATE(2025,12,1)) -> 79 | F9: =IF(ABS(D9)<=0.15,"OK","MISMATCH") -> OK
A10: Jan 26 | B10: =SUM('FY26 Revenue'!J2:J80) -> 659.3 | C10: =SUMIFS(Account_Setup_and_Data_Load!T:T,Account_Setup_and_Data_Load!L:L,DATE(2026,1,1)) -> 659.3 | D10: =ROUND(C10-B10,2) -> 0 | E10: =COUNTIF(Account_Setup_and_Data_Load!L:L,DATE(2026,1,1)) -> 79 | F10: =IF(ABS(D10)<=0.15,"OK","MISMATCH") -> OK
A11: Feb 26 | B11: =SUM('FY26 Revenue'!K2:K80) -> 769 | C11: =SUMIFS(Account_Setup_and_Data_Load!T:T,Account_Setup_and_Data_Load!L:L,DATE(2026,2,1)) -> 769 | D11: =ROUND(C11-B11,2) -> 0 | E11: =COUNTIF(Account_Setup_and_Data_Load!L:L,DATE(2026,2,1)) -> 79 | F11: =IF(ABS(D11)<=0.15,"OK","MISMATCH") -> OK
A12: 46082 | B12: =SUM('FY26 Revenue'!L2:L80) -> 845.8 | C12: =SUMIFS(Account_Setup_and_Data_Load!T:T,Account_Setup_and_Data_Load!L:L,DATE(2026,3,1)) -> 845.8 | D12: =ROUND(C12-B12,2) -> 0 | E12: =COUNTIF(Account_Setup_and_Data_Load!L:L,DATE(2025,12,1)) -> 79 | F12: =IF(ABS(D12)<=0.15,"OK","MISMATCH") -> OK
A14: Note: Dec Intra Elim has a known 0.1 rounding difference from source data entry (pre-existing, not introduced by this process).
