Workbook

Sheet Account_Setup_and_Data_Load
A1: Organization Link | B1: Organization | C1: Location | D1: Location Ref | E1: Account Style Link | F1: Account Style Caption | G1: Account Subtype | H1: Account Number | I1: Account Reference | J1: Account Supplier | K1: Account Reader | L1: Record Start YYYY-MM-DD | M1: Record End YYYY-MM-DD | N1: Record Data Quality | O1: Record Billing Type | P1: Record Subtype | Q1: Record Entry Method | R1: Record Reference | S1: Record Invoice Number | T1: Quantity | U1: Total Cost
A2: 37395 | B2: Downer | C2: REV_Allied Asphalt | D2: AASPHT | E2: 7868 | F2: Revenue - AUD Million | H2: FY27REV_Allied Asphalt | I2: FY27REV_Allied Asphalt | J2: Downer | K2: Revenue | L2: 2026-07-01 | M2: 2026-07-31 | N2: Actual | O2: Standard | Q2: Insert | R2: Allied Asphalt | S2: Allied Asphalt | T2: 0
A3: 37395 | B3: Downer | C3: REV_BIA | D3: RSV175-1 | E3: 7868 | F3: Revenue - AUD Million | H3: FY27REV_BIA | I3: FY27REV_BIA | J3: Downer | K3: Revenue | L3: 2026-07-01 | M3: 2026-07-31 | N3: Actual | O3: Standard | Q3: Insert | R3: BIA | S3: BIA | T3: -3.8
A4: 37395 | B4: Downer | C4: REV_EDI Rail- Bombardier Transportation | D4: ERBT | E4: 7868 | F4: Revenue - AUD Million | H4: FY27REV_EDI Rail- Bombardier Transportation | I4: FY27REV_EDI Rail- Bombardier Transportation | J4: Downer | K4: Revenue | L4: 2026-07-01 | M4: 2026-07-31 | N4: Actual | O4: Standard | Q4: Insert | R4: EDI Rail- Bombardier Transportation | S4: EDI Rail- Bombardier Transportation | T4: -3.4
A5: 37395 | B5: Downer | C5: REV_Emulco | D5: EMU | E5: 7868 | F5: Revenue - AUD Million | H5: FY27REV_Emulco | I5: FY27REV_Emulco | J5: Downer | K5: Revenue | L5: 2026-07-01 | M5: 2026-07-31 | N5: Actual | O5: Standard | Q5: Insert | R5: Emulco | S5: Emulco | T5: 0
A6: 37395 | B6: Downer | C6: REV_Isaac Asphalt | D6: ISAAT | E6: 7868 | F6: Revenue - AUD Million | H6: FY27REV_Isaac Asphalt | I6: FY27REV_Isaac Asphalt | J6: Downer | K6: Revenue | L6: 2026-07-01 | M6: 2026-07-31 | N6: Actual | O6: Standard | Q6: Insert | R6: Isaac Asphalt | S6: Isaac Asphalt | T6: 0

Sheet Prep - with formulas
A1: Organization Link | B1: Organization | C1: Location | D1: Location Ref | E1: Account Style Link | F1: Account Style Caption | G1: Account Subtype | H1: Account Number | I1: Account Reference | J1: Account Supplier | K1: Account Reader | L1: Record Start YYYY-MM-DD | M1: Record End YYYY-MM-DD | N1: Record Data Quality | O1: Record Billing Type | P1: Record Subtype | Q1: Record Entry Method | R1: Record Reference | S1: Record Invoice Number | T1: Quantity
A2: 37395 | B2: Downer | C2: =CONCATENATE("REV_",'FY27 JV Rev'!$A2) -> REV_Allied Asphalt | D2: =IFERROR(INDEX('Extract_for_Locations 26 Aug 26'!$E:$E,MATCH(C2,'Extract_for_Locations 26 Aug 26'!$B:$B,0)),IFERROR(INDEX('Extract_for_Locations 26 Aug 26'!$E:$E,MATCH("_CLOSED_"&C2,'Extract_for_Locations 26 Aug 26'!$B:$B,0)),"")) -> AASPHT | E2: 7868 | F2: Revenue - AUD Million | H2: =CONCATENATE("FY27REV_",'FY27 JV Rev'!$A2) -> FY27REV_Allied Asphalt | I2: =CONCATENATE("FY27REV_",'FY27 JV Rev'!$A2) -> FY27REV_Allied Asphalt | J2: Downer | K2: Revenue | L2: 2026-07-01 | M2: 2026-07-31 | N2: Actual | O2: Standard | Q2: Insert | R2: ='FY27 JV Rev'!$A2 -> Allied Asphalt | S2: ='FY27 JV Rev'!$A2 -> Allied Asphalt | T2: =-'FY27 JV Rev'!B2 -> 0
A3: 37395 | B3: Downer | C3: =CONCATENATE("REV_",'FY27 JV Rev'!$A3) -> REV_BIA | D3: =IFERROR(INDEX('Extract_for_Locations 26 Aug 26'!$E:$E,MATCH(C3,'Extract_for_Locations 26 Aug 26'!$B:$B,0)),IFERROR(INDEX('Extract_for_Locations 26 Aug 26'!$E:$E,MATCH("_CLOSED_"&C3,'Extract_for_Locations 26 Aug 26'!$B:$B,0)),"")) -> RSV175-1 | E3: 7868 | F3: Revenue - AUD Million | H3: =CONCATENATE("FY27REV_",'FY27 JV Rev'!$A3) -> FY27REV_BIA | I3: =CONCATENATE("FY27REV_",'FY27 JV Rev'!$A3) -> FY27REV_BIA | J3: Downer | K3: Revenue | L3: 2026-07-01 | M3: 2026-07-31 | N3: Actual | O3: Standard | Q3: Insert | R3: ='FY27 JV Rev'!$A3 -> BIA | S3: ='FY27 JV Rev'!$A3 -> BIA | T3: =-'FY27 JV Rev'!B3 -> -3.8
A4: 37395 | B4: Downer | C4: =CONCATENATE("REV_",'FY27 JV Rev'!$A4) -> REV_EDI Rail- Bombardier Transportation | D4: =IFERROR(INDEX('Extract_for_Locations 26 Aug 26'!$E:$E,MATCH(C4,'Extract_for_Locations 26 Aug 26'!$B:$B,0)),IFERROR(INDEX('Extract_for_Locations 26 Aug 26'!$E:$E,MATCH("_CLOSED_"&C4,'Extract_for_Locations 26 Aug 26'!$B:$B,0)),"")) -> ERBT | E4: 7868 | F4: Revenue - AUD Million | H4: =CONCATENATE("FY27REV_",'FY27 JV Rev'!$A4) -> FY27REV_EDI Rail- Bombardier Transportation | I4: =CONCATENATE("FY27REV_",'FY27 JV Rev'!$A4) -> FY27REV_EDI Rail- Bombardier Transportation | J4: Downer | K4: Revenue | L4: 2026-07-01 | M4: 2026-07-31 | N4: Actual | O4: Standard | Q4: Insert | R4: ='FY27 JV Rev'!$A4 -> EDI Rail- Bombardier Transportation | S4: ='FY27 JV Rev'!$A4 -> EDI Rail- Bombardier Transportation | T4: =-'FY27 JV Rev'!B4 -> -3.4
A5: 37395 | B5: Downer | C5: =CONCATENATE("REV_",'FY27 JV Rev'!$A5) -> REV_Emulco | D5: =IFERROR(INDEX('Extract_for_Locations 26 Aug 26'!$E:$E,MATCH(C5,'Extract_for_Locations 26 Aug 26'!$B:$B,0)),IFERROR(INDEX('Extract_for_Locations 26 Aug 26'!$E:$E,MATCH("_CLOSED_"&C5,'Extract_for_Locations 26 Aug 26'!$B:$B,0)),"")) -> EMU | E5: 7868 | F5: Revenue - AUD Million | H5: =CONCATENATE("FY27REV_",'FY27 JV Rev'!$A5) -> FY27REV_Emulco | I5: =CONCATENATE("FY27REV_",'FY27 JV Rev'!$A5) -> FY27REV_Emulco | J5: Downer | K5: Revenue | L5: 2026-07-01 | M5: 2026-07-31 | N5: Actual | O5: Standard | Q5: Insert | R5: ='FY27 JV Rev'!$A5 -> Emulco | S5: ='FY27 JV Rev'!$A5 -> Emulco | T5: =-'FY27 JV Rev'!B5 -> 0
A6: 37395 | B6: Downer | C6: =CONCATENATE("REV_",'FY27 JV Rev'!$A6) -> REV_Isaac Asphalt | D6: =IFERROR(INDEX('Extract_for_Locations 26 Aug 26'!$E:$E,MATCH(C6,'Extract_for_Locations 26 Aug 26'!$B:$B,0)),IFERROR(INDEX('Extract_for_Locations 26 Aug 26'!$E:$E,MATCH("_CLOSED_"&C6,'Extract_for_Locations 26 Aug 26'!$B:$B,0)),"")) -> ISAAT | E6: 7868 | F6: Revenue - AUD Million | H6: =CONCATENATE("FY27REV_",'FY27 JV Rev'!$A6) -> FY27REV_Isaac Asphalt | I6: =CONCATENATE("FY27REV_",'FY27 JV Rev'!$A6) -> FY27REV_Isaac Asphalt | J6: Downer | K6: Revenue | L6: 2026-07-01 | M6: 2026-07-31 | N6: Actual | O6: Standard | Q6: Insert | R6: ='FY27 JV Rev'!$A6 -> Isaac Asphalt | S6: ='FY27 JV Rev'!$A6 -> Isaac Asphalt | T6: =-'FY27 JV Rev'!B6 -> 0

Sheet FY27 JV Rev
A1: Joint Venture and Associates | B1: Jul
A2: Allied Asphalt | B2: 0
A3: BIA | B3: 3.8
A4: EDI Rail- Bombardier Transportation | B4: 3.4
A5: Emulco | B5: 0
A6: Isaac Asphalt | B6: 0
A8: Group | B8: 7.2
A9: Check | B9: =B8-SUM(B2:B6) -> 0

Sheet FY27 JV Revenue
A1: FY27 JV Revenue — Joint Ventures & Associates (Jul 26 – Jun 27; one month deep: Jul 26)
A2: Source: sheet "FY27 JV Rev" (copied verbatim into this workbook from "Actual Revenue Jul 26 -unlinked.xlsx"). Cells below link to it. The Account_Setup_and_Data_Load sheet carries these same amounts NEGATED, to exclude JV revenue from all revenue figures — see "Prep - with formulas" for the row-by-row linking.
A4: Joint Venture and Associates | B4: Jul 26 | C4: FY27 Total | D4: Location Ref | E4: Already in FY27 revenue upload?
A5: Allied Asphalt | B5: ='FY27 JV Rev'!B2 -> 0 | C5: =SUM(B5:B5) -> 0 | D5: =IFERROR(INDEX('Extract_for_Locations 26 Aug 26'!$E:$E,MATCH("REV_"&$A5,'Extract_for_Locations 26 Aug 26'!$B:$B,0)),IFERROR(INDEX('Extract_for_Locations 26 Aug 26'!$E:$E,MATCH("_CLOSED_"&"REV_"&$A5,'Extract_for_Locations 26 Aug 26'!$B:$B,0)),"")) -> AASPHT | E5: No — see note 4
A6: BIA | B6: ='FY27 JV Rev'!B3 -> 3.8 | C6: =SUM(B6:B6) -> 3.8 | D6: =IFERROR(INDEX('Extract_for_Locations 26 Aug 26'!$E:$E,MATCH("REV_"&$A6,'Extract_for_Locations 26 Aug 26'!$B:$B,0)),IFERROR(INDEX('Extract_for_Locations 26 Aug 26'!$E:$E,MATCH("_CLOSED_"&"REV_"&$A6,'Extract_for_Locations 26 Aug 26'!$B:$B,0)),"")) -> RSV175-1 | E6: Yes — inside the REV_Transport & Infrastructure AU roll-up, see note 4
A7: EDI Rail- Bombardier Transportation | B7: ='FY27 JV Rev'!B4 -> 3.4 | C7: =SUM(B7:B7) -> 3.4 | D7: =IFERROR(INDEX('Extract_for_Locations 26 Aug 26'!$E:$E,MATCH("REV_"&$A7,'Extract_for_Locations 26 Aug 26'!$B:$B,0)),IFERROR(INDEX('Extract_for_Locations 26 Aug 26'!$E:$E,MATCH("_CLOSED_"&"REV_"&$A7,'Extract_for_Locations 26 Aug 26'!$B:$B,0)),"")) -> ERBT | E7: Yes — as the "WA JV" line under TLS Fleet, inside the REV_Passenger Through Life Support roll-up, see note 4
A8: Emulco | B8: ='FY27 JV Rev'!B5 -> 0 | C8: =SUM(B8:B8) -> 0 | D8: =IFERROR(INDEX('Extract_for_Locations 26 Aug 26'!$E:$E,MATCH("REV_"&$A8,'Extract_for_Locations 26 Aug 26'!$B:$B,0)),IFERROR(INDEX('Extract_for_Locations 26 Aug 26'!$E:$E,MATCH("_CLOSED_"&"REV_"&$A8,'Extract_for_Locations 26 Aug 26'!$B:$B,0)),"")) -> EMU | E8: No — see note 4
A9: Isaac Asphalt | B9: ='FY27 JV Rev'!B6 -> 0 | C9: =SUM(B9:B9) -> 0 | D9: =IFERROR(INDEX('Extract_for_Locations 26 Aug 26'!$E:$E,MATCH("REV_"&$A9,'Extract_for_Locations 26 Aug 26'!$B:$B,0)),IFERROR(INDEX('Extract_for_Locations 26 Aug 26'!$E:$E,MATCH("_CLOSED_"&"REV_"&$A9,'Extract_for_Locations 26 Aug 26'!$B:$B,0)),"")) -> ISAAT | E9: No — see note 4
A10: Group | B10: =SUM(B5:B9) -> 7.2 | C10: =SUM(C5:C9) -> 7.2
A12: Notes
A13: 1. Purpose: JV and associate revenue is to be excluded from all revenue figures. This workbook uploads the JV revenue as negative values against JV-specific locations, so revenue reporting nets to revenue excluding JV revenue. It is the FY27 counterpart of Account_Setup_and_Data_Load_-_PM&C_JVREVJUL25toJUN26_Setup.xlsx (FY26), one month deep so far (Jul 26); extend it month by month alongside the main FY27 setup workbook.
A14: 2. Locations: per the "Extract_for_Locations 26 Aug 26" sheet (copied verbatim into this workbook from the FY27 setup workbook), all five JV revenue locations exist in Envizi as open "REV_<name>" locations — they were reopened for the FY26 exclusion load, so unlike FY26 no reopening/renaming is needed before loading. Each carries both the Classification (Operational Control) and Portfolio (Revenue) memberships. The Location Refs in column D are derived from that extract by INDEX/MATCH (matching "REV_<name>", with the FY26 fallback to "_CLOSED_REV_<name>" retained in case a location is ever closed again), as is column D of "Prep - with formulas".
A15: 3. Sign convention: the monthly figures on this sheet are JV revenue as reported (positive), linked from the verbatim "FY27 JV Rev" source sheet. The negation is applied in "Prep - with formulas" (Quantity column: =-'FY27 JV Rev'!<cell>) and the upload sheet carries the resulting values. Values of zero are loaded as 0.
A16: 4. Coverage — CONFIRMED 27 Aug 26: all five JVs are uploaded as negatives at the JV-source figures, matching the FY26 treatment (coverage there confirmed 4 Aug 26), on the basis that JV revenue is included in the main revenue tab by default. For Jul 26: BIA (3.8) is in the loaded FY27 revenue rolled into REV_Transport & Infrastructure AU (the FY27 workbook rolls to Sub-LOB × Level 2, and BIA is a Level 2 under Transport & Infrastructure AU); EDI Rail- Bombardier Transportation is in it as the "WA JV" line under TLS Fleet, rolled into REV_Passenger Through Life Support. Allied Asphalt, Emulco and Isaac Asphalt are zero in Jul 26; in months where they are non-zero their revenue sits inside the divisional lines rather than as own lines.
A17: 4a. Rounding: the deduction uses the JV-source figures, which can differ from the main tab by rounding — for Jul 26, "WA JV" is 3.5 in the main tab but EDI is 3.4 on the JV sheet, leaving a 0.1 residual in net revenue. Same class of residual as FY26 (note 4a there: BIA 69.9 vs 70.1). NOTE the FY26 workbook's note 4 states EDI Rail- Bombardier was "not previously included" in the FY26 figures — that is incorrect: it is included there too, as the "WA JV" line under RTS > TLS Fleet (35.9 in FY26 vs 35.6 deducted). The FY26 loaded amounts are unaffected; only that note's rationale is wrong.
A18: 5. Keolis Downer JV: not on the "FY27 JV Rev" source sheet. Per the FY26 decision (confirmed 4 Aug 26), the source sheet is the agreed definition of JV revenue to exclude, so Keolis Downer revenue stays in revenue.
A19: 6. Accounts: the five FY27REV_<name> accounts do not exist yet in the 26 Aug 26 accounts extract (their FY26REV_ counterparts do, created by the FY26 exclusion load). Accounts do not need creating separately — this data load creates them alongside the records (Record Entry Method Insert).
A20: 7. BIA Location Ref: the extract shows Location Ref "RSV175-1" for REV_BIA, which looks like a Rail Services Victoria code. Copied faithfully from the extract, unchanged from FY26.

Sheet Extract_for_Locations 26 Aug 26
A1: Associate | B1: Location_Name | C1: Type | D1: Ref_No | E1: Location Ref | F1: Id | G1: Notes | H1: Address | I1: City | J1: State | K1: Postal_Code | L1: Address Country | M1: Region | N1: Country | O1: Alternate Factor Region | P1: Group Level 1 | Q1: Group Level 2 | R1: Group Level 3 | S1: Group_Associate | T1: Report_Percent | U1: Effective_From | V1: Effective_To | W1: Group_Type | X1: Latitude | Y1: Longitude | Z1: ANZSIC Code | AA1: Opened On | AB1: Closed On
A2: Downer | B2: .HOUR.LMC -RICHTER DRI'G PNG CENTURY R | C2: Other | D2: L9.MIN.UED.4501 | E2: 4501 | M2: Auckland | N2: New Zealand | P2: Operational Control | Q2: Operational Control | R2: Mining | S2: Downer | T2: 100.0000 | W2: Classification
A3: Downer | B3: .HOUR.RICHTER DRILLING - OK TEDI | C3: Other | D3: L9.MIN.UED.4502 | E3: 4502 | M3: Auckland | N3: New Zealand | P3: Operational Control | Q3: Operational Control | R3: Mining | S3: Downer | T3: 100.0000 | W3: Classification
A4: Downer | B4: [CLOSED] 4 Redwood Lane - Tauriko West Enabling Works | C4: Depot | D4: L9.DNZJ.553912 | E4: L9.DNZJ.553912 | M4: Bay of Plenty | N4: New Zealand | P4: Operational Control | Q4: Operational Control | R4: Transport & Infrastructure (T&I) | S4: Downer | T4: 100.0000 | W4: Classification | AB4: 2026/03/31
A5: Downer | B5: [CLOSED] Hobart Airport Upgrade Project | C5: Airport | D5: L9.J.170751 | E5: 170751 | G5: TI-170751 - Airports General Delivery | H5: 250 Surf Road, Seven Mile Beach | I5: Tasmania | J5: TAS | K5: 7170 | M5: Tasmania | N5: Australia | P5: Operational Control | Q5: Operational Control | R5: Transport & Infrastructure (T&I) | S5: Downer | T5: 100.0000 | W5: Classification | AB5: 2025/05/31
A6: Downer | B6: [CLOSED] Numurkah Solar Farm | C6: Other | D6: L9.J.381155 | E6: IP-39210265 | M6: Shepparton | N6: Australia | P6: Y_Non Operational Control | Q6: Y_Non Operational Control | R6: Energy and Utilities (EU) | S6: Downer | T6: 100.0000 | W6: Classification | X6: -37.819015 | Y6: 144.955762 | Z6: 310
A7: Downer | B7: _AI Testing | C7: Other | M7: North Ryde | N7: Australia | P7: Y_Non Operational Control | Q7: Y_Non Operational Control | R7: Corporate | S7: Downer | T7: 100.0000 | W7: Classification
A8: Downer | B8: _CLOSED_ AGIS Braddon | C8: Office | D8: L9.J.502002 | E8: 2001 | F8: 2001 | G8: electricity data only from landlord accounts | M8: Australian Capital Territory | N8: Australia | P8: Operational Control | Q8: Operational Control | R8: Social Infra & Citizen Serv (SICS) | S8: Downer | T8: 100.0000 | U8: 2018/11/01 | V8: 2021/10/31 | W8: Classification | X8: -35.273 | Y8: 149.133 | Z8: 760 | AA8: 2016/08/01 | AB8: 2022/12/06
A9: Downer | B9: _CLOSED_ North Ryde T1 - Level 2 | C9: Office | D9: L9.J.102001 | E9: 1012 | H9: T1, Triniti Business Campus, 39 Delhi Road | I9: Sydney | J9: NSW | K9: 2113 | M9: North Ryde | N9: Australia | P9: Operational Control | Q9: Operational Control | R9: Corporate | S9: Downer | T9: 100.0000 | W9: Classification | Z9: 729 | AB9: 1900/01/01
A10: Downer | B10: _CLOSED_ OSM_Waitaki | C10: Other | D10: L9.DNZJ.55876 | E10: 5088 | G10: Outside Space Management (Gardening) - New facilities established for more granular reporting and to reflect new structure for FY17. See facility named "NZ-Infrastructure Services" for historical data. | H10: Chelmer Street | I10: Oamaru | J10: Otago | K10: 2104 | L10: New Zealand | M10: Oamaru | N10: New Zealand | P10: Operational Control | Q10: Operational Control | R10: Transport & Infrastructure (T&I) | S10: Downer | T10: 100.0000 | W10: Classification | X10: -45.0978481999999 | Y10: 170.9606991 | Z10: 731 | AA10: 2017/07/01
A11: Downer | B11: _CLOSED_25820008 - Winneke Main Substation Switchboard Replacement | C11: Site | D11: L9.J.25820008 | E11: UTIL-25820008 | G11: Main Substation Switchboard Replacement - Project finished in September 2022. | M11: Victoria | N11: Australia | P11: Operational Control | Q11: Operational Control | R11: Energy and Utilities (EU) | S11: Downer | T11: 100.0000 | W11: Classification | AB11: 2022/10/01
A12: Downer | B12: _CLOSED_25820008 - Winneke Main Substation Switchboard Replacement | C12: Site | D12: L9.J.25820008 | E12: UTIL-25820008 | G12: Main Substation Switchboard Replacement - Project finished in September 2022. | M12: Victoria | N12: Australia | P12: Utilities | Q12: UTIL-252 - Water Services Projects NSW/VIC | R12: SFP JV | S12: Downer | T12: 100.0000 | W12: Portfolio | AB12: 2022/10/01
A13: Downer | B13: _CLOSED_25820012 - WTP 25W Lagoon Pond 1 HV and LV Renewals | C13: Site | D13: L9.J.25820012 | E13: UTIL-25820012 | G13: WTP 25W Lagoon Pond 1 HV and LV Renewals | M13: Victoria | N13: Australia | P13: Operational Control | Q13: Operational Control | R13: Energy and Utilities (EU) | S13: Downer | T13: 100.0000 | W13: Classification | AB13: 2024/12/03
A14: Downer | B14: _CLOSED_25820012 - WTP 25W Lagoon Pond 1 HV and LV Renewals | C14: Site | D14: L9.J.25820012 | E14: UTIL-25820012 | G14: WTP 25W Lagoon Pond 1 HV and LV Renewals | M14: Victoria | N14: Australia | P14: Utilities | Q14: UTIL-252 - Water Services Projects NSW/VIC | R14: SFP JV | S14: Downer | T14: 100.0000 | W14: Portfolio | AB14: 2024/12/03
A15: Downer | B15: _CLOSED_86 Collins St Tas | C15: Branch Office | D15: L9.J.105001 | E15: 9164 | G15: Level 12, 86 Collins Street HOBART TAS 7000 | M15: Hobart | N15: Australia | P15: Operational Control | Q15: Operational Control | R15: Corporate | S15: Downer | T15: 100.0000 | W15: Classification | Z15: 692
A16: Downer | B16: _CLOSED_Accommodation - NZ | C16: Hotel | D16: L9.WAU.000887 | E16: L9.WAU.000887 | M16: Auckland | N16: New Zealand | P16: Operational Control | Q16: Operational Control | R16: Corporate | S16: Downer | T16: 100.0000 | W16: Classification
A17: Downer | B17: _CLOSED_Accommodation NT | C17: Facility | E17: 9129 | G17: 55 BATTEN RD MARRARA | M17: Darwin | N17: Australia | P17: Z_HISTORICAL_Operational Control | Q17: Z_HISTORICAL_Operational Control | R17: Corporate | S17: Downer | T17: 100.0000 | W17: Classification
A18: Downer | B18: _CLOSED_ACES - North Queensland Region | C18: Depot | D18: L9.DUA.12005 | E18: L9.DUA.12005 | G18: Contract ended June 2022. | M18: Queensland | N18: Australia | P18: Operational Control | Q18: Operational Control | R18: Energy and Utilities (EU) | S18: Downer | T18: 100.0000 | W18: Classification | AB18: 2022/06/30
A19: Downer | B19: _CLOSED_ACT | C19: Plant | D19: L9.S.11000020 | E19: L9.S.11000020 | G19: Unallocated regional fuel accounts | H19: ACT | I19: ACT | J19: ACT | M19: Australian Capital Territory | N19: Australia | P19: Z_HISTORICAL_Operational Control | Q19: Z_HISTORICAL_Operational Control | R19: Corporate | S19: Downer | T19: 100.0000 | W19: Classification | Z19: 580
A20: Downer | B20: _CLOSED_Adelaide Light Rail - North Terrace Tramli | C20: Other | D20: L9.D.20143004 | E20: L9.D.20143004 | H20: SA | I20: Adelaide | J20: SA | M20: South Australia | N20: Australia | P20: DT Infrastructure Locations for reallocation | Q20: DT Infrastructure Locations for reallocation | R20: DT Infrastructure Locations for reallocation | S20: Downer | T20: 100.0000 | W20: Portfolio | X20: -34.921297 | Y20: 138.604655 | Z20: 310
A21: Downer | B21: _CLOSED_Adelaide Light Rail - North Terrace Tramli | C21: Other | D21: L9.D.20143004 | E21: L9.D.20143004 | H21: SA | I21: Adelaide | J21: SA | M21: South Australia | N21: Australia | P21: Operational Control | Q21: Operational Control | R21: DT Infrastructure (pre Sept 23 divestment) | S21: Downer | T21: 100.0000 | V21: 2023/09/30 | W21: Classification | X21: -34.921297 | Y21: 138.604655 | Z21: 310
A22: Downer | B22: _CLOSED_Adelaide Light Rail - North Terrace Tramli | C22: Other | D22: L9.D.20143004 | E22: L9.D.20143004 | H22: SA | I22: Adelaide | J22: SA | M22: South Australia | N22: Australia | P22: Y_Non Operational Control | Q22: Y_Non Operational Control | R22: DT Infrastructure (post Sept Divestment) | S22: Downer | T22: 100.0000 | U22: 2023/10/01 | W22: Classification | X22: -34.921297 | Y22: 138.604655 | Z22: 310
A23: Downer | B23: _CLOSED_AE Smith - Burleigh | C23: Branch Office | D23: L9.S.13000757 | E23: 9165 | G23: 12/8 Fortitude Crescent BURLEIGH HEADS QLD 4220 | M23: New South Wales | N23: Australia | P23: ADS Backup | Q23: ADS Backup | R23: ADS Backup | S23: Downer | T23: 100.0000 | W23: Portfolio | Z23: 692
A24: Downer | B24: _CLOSED_AE Smith - Burleigh | C24: Branch Office | D24: L9.S.13000757 | E24: 9165 | G24: 12/8 Fortitude Crescent BURLEIGH HEADS QLD 4220 | M24: New South Wales | N24: Australia | P24: Operational Control | Q24: Operational Control | R24: Asset & Development Services (Baseline) | S24: Downer | T24: 100.0000 | V24: 2023/06/30 | W24: Classification | Z24: 692
A25: Downer | B25: _CLOSED_AE Smith - Burleigh | C25: Branch Office | D25: L9.S.13000757 | E25: 9165 | G25: 12/8 Fortitude Crescent BURLEIGH HEADS QLD 4220 | M25: New South Wales | N25: Australia | P25: Z_DIVESTED_Operational Control | Q25: Z_DIVESTED_Operational Control | R25: Asset & Development Services (FY24 & Beyond) | S25: Downer | T25: 100.0000 | U25: 2023/07/01 | W25: Classification | Z25: 692
A26: Downer | B26: _CLOSED_AE Smith - Canning Vale | C26: Wharf | D26: L9.S.16015134 | E26: Loc Ref | H26: 15 Canvale Rd | I26: Canning Vale | J26: WA | K26: 6155 | L26: Australia | M26: Western Australia | N26: Australia | P26: Z_HISTORICAL_Operational Control | Q26: Z_HISTORICAL_Operational Control | R26: Asset & Development Services (ADS) | S26: Downer | T26: 100.0000 | W26: Classification
A27: Downer | B27: _CLOSED_AE Smith - Eagle Farm | C27: Branch Office | D27: L9.S.16015125 | E27: 9013 | H27: Lot 801 65 Links Ave | I27: Eagle Farm | J27: QLD | K27: 4009 | M27: Queensland | N27: Australia | P27: ADS Backup | Q27: ADS Backup | R27: ADS Backup | S27: Downer | T27: 100.0000 | W27: Portfolio | X27: -27.436443 | Y27: 153.086368 | Z27: 692
A28: Downer | B28: _CLOSED_AE Smith - Eagle Farm | C28: Branch Office | D28: L9.S.16015125 | E28: 9013 | H28: Lot 801 65 Links Ave | I28: Eagle Farm | J28: QLD | K28: 4009 | M28: Queensland | N28: Australia | P28: Operational Control | Q28: Operational Control | R28: Asset & Development Services (Baseline) | S28: Downer | T28: 100.0000 | V28: 2023/06/30 | W28: Classification | X28: -27.436443 | Y28: 153.086368 | Z28: 692
A29: Downer | B29: _CLOSED_AE Smith - Eagle Farm | C29: Branch Office | D29: L9.S.16015125 | E29: 9013 | H29: Lot 801 65 Links Ave | I29: Eagle Farm | J29: QLD | K29: 4009 | M29: Queensland | N29: Australia | P29: Z_DIVESTED_Operational Control | Q29: Z_DIVESTED_Operational Control | R29: Asset & Development Services (FY24 & Beyond) | S29: Downer | T29: 100.0000 | U29: 2023/07/01 | W29: Classification | X29: -27.436443 | Y29: 153.086368 | Z29: 692
A30: Downer | B30: _CLOSED_AE Smith - Eagle Farm, Harvey St | C30: Office | D30: L9.S.13001004 | E30: 9128 | H30: Harvey St | I30: Eagle Farm | J30: QLD | K30: 4009 | M30: Brisbane | N30: Australia | P30: ADS Backup | Q30: ADS Backup | R30: ADS Backup | S30: Downer | T30: 100.0000 | W30: Portfolio | X30: -27.437252 | Y30: 153.093614 | Z30: 692
A31: Downer | B31: _CLOSED_AE Smith - Eagle Farm, Harvey St | C31: Office | D31: L9.S.13001004 | E31: 9128 | H31: Harvey St | I31: Eagle Farm | J31: QLD | K31: 4009 | M31: Brisbane | N31: Australia | P31: Operational Control | Q31: Operational Control | R31: Asset & Development Services (Baseline) | S31: Downer | T31: 100.0000 | V31: 2023/06/30 | W31: Classification | X31: -27.437252 | Y31: 153.093614 | Z31: 692
A32: Downer | B32: _CLOSED_AE Smith - Eagle Farm, Harvey St | C32: Office | D32: L9.S.13001004 | E32: 9128 | H32: Harvey St | I32: Eagle Farm | J32: QLD | K32: 4009 | M32: Brisbane | N32: Australia | P32: Z_DIVESTED_Operational Control | Q32: Z_DIVESTED_Operational Control | R32: Asset & Development Services (FY24 & Beyond) | S32: Downer | T32: 100.0000 | U32: 2023/07/01 | W32: Classification | X32: -27.437252 | Y32: 153.093614 | Z32: 692
A33: Downer | B33: _CLOSED_AE Smith - Eagle Farm, Schneider Rd | C33: Branch Office | D33: L9.S.13001052 | E33: 9127 | H33: 80 Schneider Road | I33: Eagle Farm | J33: QLD | K33: 4009 | L33: Australia | M33: Brisbane | N33: Australia | P33: ADS Backup | Q33: ADS Backup | R33: ADS Backup | S33: Downer | T33: 100.0000 | W33: Portfolio | X33: -27.423892 | Y33: 153.085062 | Z33: 692
A34: Downer | B34: _CLOSED_AE Smith - Eagle Farm, Schneider Rd | C34: Branch Office | D34: L9.S.13001052 | E34: 9127 | H34: 80 Schneider Road | I34: Eagle Farm | J34: QLD | K34: 4009 | L34: Australia | M34: Brisbane | N34: Australia | P34: Operational Control | Q34: Operational Control | R34: Asset & Development Services (Baseline) | S34: Downer | T34: 100.0000 | V34: 2023/06/30 | W34: Classification | X34: -27.423892 | Y34: 153.085062 | Z34: 692
A35: Downer | B35: _CLOSED_AE Smith - Eagle Farm, Schneider Rd | C35: Branch Office | D35: L9.S.13001052 | E35: 9127 | H35: 80 Schneider Road | I35: Eagle Farm | J35: QLD | K35: 4009 | L35: Australia | M35: Brisbane | N35: Australia | P35: Z_DIVESTED_Operational Control | Q35: Z_DIVESTED_Operational Control | R35: Asset & Development Services (FY24 & Beyond) | S35: Downer | T35: 100.0000 | U35: 2023/07/01 | W35: Classification | X35: -27.423892 | Y35: 153.085062 | Z35: 692
A36: Downer | B36: _CLOSED_AE Smith - Knoxfield | C36: Wharf | D36: L9.S.16012601 | H36: 10 Brand Rd | I36: Knoxfield | J36: VIC | K36: 3180 | M36: Victoria | N36: Australia | P36: Z_HISTORICAL_Operational Control | Q36: Z_HISTORICAL_Operational Control | R36: Asset & Development Services (ADS) | S36: Downer | T36: 100.0000 | W36: Classification
A37: Downer | B37: _CLOSED_AE Smith - Mackay | C37: Branch Office | D37: L9.S.3197.003.020.9M | E37: 9012 | H37: U4, 269 Richardson Rd | I37: Kawana | J37: QLD | K37: 4701 | L37: Australia | M37: Queensland | N37: Australia | P37: Z_HISTORICAL_Operational Control | Q37: Z_HISTORICAL_Operational Control | R37: Asset & Development Services (ADS) | S37: Downer | T37: 100.0000 | W37: Classification | Z37: 696
A38: Downer | B38: _CLOSED_AE Smith - Manunda | C38: Wharf | H38: 1/13 Donaldson St | I38: Manunda | J38: QLD | K38: 4870 | M38: Queensland | N38: Australia | P38: Z_HISTORICAL_Operational Control | Q38: Z_HISTORICAL_Operational Control | R38: Asset & Development Services (ADS) | S38: Downer | T38: 100.0000 | W38: Classification
A39: Downer | B39: _CLOSED_AE Smith - Mornington | C39: Branch Office | D39: L9.S.13001061 | E39: 9014 | H39: U 2 4 Yamada Place | I39: Mornington | J39: TAS | K39: 7018 | L39: Australia | M39: Tasmania | N39: Australia | P39: ADS Backup | Q39: ADS Backup | R39: ADS Backup | S39: Downer | T39: 100.0000 | W39: Portfolio | X39: -42.862696 | Y39: 147.399802 | Z39: 692
A40: Downer | B40: _CLOSED_AE Smith - Mornington | C40: Branch Office | D40: L9.S.13001061 | E40: 9014 | H40: U 2 4 Yamada Place | I40: Mornington | J40: TAS | K40: 7018 | L40: Australia | M40: Tasmania | N40: Australia | P40: Operational Control | Q40: Operational Control | R40: Asset & Development Services (Baseline) | S40: Downer | T40: 100.0000 | V40: 2023/06/30 | W40: Classification | X40: -42.862696 | Y40: 147.399802 | Z40: 692
A41: Downer | B41: _CLOSED_AE Smith - Mornington | C41: Branch Office | D41: L9.S.13001061 | E41: 9014 | H41: U 2 4 Yamada Place | I41: Mornington | J41: TAS | K41: 7018 | L41: Australia | M41: Tasmania | N41: Australia | P41: Z_DIVESTED_Operational Control | Q41: Z_DIVESTED_Operational Control | R41: Asset & Development Services (FY24 & Beyond) | S41: Downer | T41: 100.0000 | U41: 2023/07/01 | W41: Classification | X41: -42.862696 | Y41: 147.399802 | Z41: 692
A42: Downer | B42: _CLOSED_AE Smith - Mortlake | C42: Branch Office | D42: L9.S.13000753 | E42: 9015 | G42: Moved to Victoria Road, Gladesville from 1/6/2019 | H42: 13-15 McDonald St | I42: Mortlake | J42: NSW | K42: 2137 | M42: New South Wales | N42: Australia | P42: Z_HISTORICAL_Operational Control | Q42: Z_HISTORICAL_Operational Control | R42: Asset & Development Services (ADS) | S42: Downer | T42: 100.0000 | V42: 2019/06/30 | W42: Classification | X42: -33.842053 | Y42: 151.106519 | Z42: 696
A43: Downer | B43: _CLOSED_AE Smith - Mulgrave | C43: Branch Office | D43: L9.S.16015131 | E43: 9016 | G43: Lease ended 2/12/2021 | H43: 21-29 Miles St | I43: Mulgrave | J43: VIC | K43: 3170 | M43: Mulgrave | N43: Australia | P43: ADS Backup | Q43: ADS Backup | R43: ADS Backup | S43: Downer | T43: 100.0000 | W43: Portfolio | X43: -37.923024 | Y43: 145.153374 | Z43: 692
A44: Downer | B44: _CLOSED_AE Smith - Mulgrave | C44: Branch Office | D44: L9.S.16015131 | E44: 9016 | G44: Lease ended 2/12/2021 | H44: 21-29 Miles St | I44: Mulgrave | J44: VIC | K44: 3170 | M44: Mulgrave | N44: Australia | P44: Operational Control | Q44: Operational Control | R44: Asset & Development Services (Baseline) | S44: Downer | T44: 100.0000 | V44: 2023/06/30 | W44: Classification | X44: -37.923024 | Y44: 145.153374 | Z44: 692
A45: Downer | B45: _CLOSED_AE Smith - Mulgrave | C45: Branch Office | D45: L9.S.16015131 | E45: 9016 | G45: Lease ended 2/12/2021 | H45: 21-29 Miles St | I45: Mulgrave | J45: VIC | K45: 3170 | M45: Mulgrave | N45: Australia | P45: Z_DIVESTED_Operational Control | Q45: Z_DIVESTED_Operational Control | R45: Asset & Development Services (FY24 & Beyond) | S45: Downer | T45: 100.0000 | U45: 2023/07/01 | W45: Classification | X45: -37.923024 | Y45: 145.153374 | Z45: 692
A46: Downer | B46: _CLOSED_AE Smith - Northgate | C46: Wharf | H46: 115 Crockford St | I46: Northgate | J46: QLD | K46: 4013 | M46: Queensland | N46: Australia | P46: Z_HISTORICAL_Operational Control | Q46: Z_HISTORICAL_Operational Control | R46: Asset & Development Services (ADS) | S46: Downer | T46: 100.0000 | W46: Classification
A47: Downer | B47: _CLOSED_AE Smith - Scoresby | C47: Branch Office | D47: L9.S.13001039 | E47: 9018 | H47: 20-22 Janine St | I47: Scoresby | J47: VIC | K47: 3179 | M47: Victoria | N47: Australia | P47: ADS Backup | Q47: ADS Backup | R47: ADS Backup | S47: Downer | T47: 100.0000 | W47: Portfolio | X47: -37.900965 | Y47: 145.230266 | Z47: 692
A48: Downer | B48: _CLOSED_AE Smith - Scoresby | C48: Branch Office | D48: L9.S.13001039 | E48: 9018 | H48: 20-22 Janine St | I48: Scoresby | J48: VIC | K48: 3179 | M48: Victoria | N48: Australia | P48: Operational Control | Q48: Operational Control | R48: Asset & Development Services (Baseline) | S48: Downer | T48: 100.0000 | V48: 2023/06/30 | W48: Classification | X48: -37.900965 | Y48: 145.230266 | Z48: 692
A49: Downer | B49: _CLOSED_AE Smith - Scoresby | C49: Branch Office | D49: L9.S.13001039 | E49: 9018 | H49: 20-22 Janine St | I49: Scoresby | J49: VIC | K49: 3179 | M49: Victoria | N49: Australia | P49: Z_DIVESTED_Operational Control | Q49: Z_DIVESTED_Operational Control | R49: Asset & Development Services (FY24 & Beyond) | S49: Downer | T49: 100.0000 | U49: 2023/07/01 | W49: Classification | X49: -37.900965 | Y49: 145.230266 | Z49: 692
A50: Downer | B50: _CLOSED_AE Smith - South Gladstone | C50: Wharf | H50: U10, 18 McCann St | I50: South Gladstone | J50: QLD | K50: 4680 | L50: Australia | M50: Queensland | N50: Australia | P50: Z_HISTORICAL_Operational Control | Q50: Z_HISTORICAL_Operational Control | R50: Asset & Development Services (ADS) | S50: Downer | T50: 100.0000 | W50: Classification
A51: Downer | B51: _CLOSED_AE Smith - Townsville | C51: Wharf | H51: 9 Corporate Cres | I51: Garbutt | J51: QLD | K51: 4814 | M51: Queensland | N51: Australia | P51: Z_HISTORICAL_Operational Control | Q51: Z_HISTORICAL_Operational Control | R51: Asset & Development Services (ADS) | S51: Downer | T51: 100.0000 | W51: Classification
A52: Downer | B52: _CLOSED_Aldoga TL - Office | C52: Office | D52: L9.J.37740112 | M52: Queensland | N52: Australia | P52: Y_Non Operational Control | Q52: Y_Non Operational Control | R52: Energy and Utilities (EU) | S52: Downer | T52: 100.0000 | W52: Classification | AB52: 2023/07/05
A53: Downer | B53: _CLOSED_Aldoga TL - Site | C53: Site | D53: L9.J.37740112 | M53: Queensland | N53: Australia | P53: Operational Control | Q53: Operational Control | R53: Energy and Utilities (EU) | S53: Downer | T53: 100.0000 | W53: Classification | AB53: 2023/07/05
A54: Downer | B54: _CLOSED_Altona-Rail | C54: Other | D54: L9.RAL.032 | E54: 1111 | H54: 7 Westlink Court | I54: Altona | J54: Victoria | K54: 3018 | L54: Australia | M54: Victoria | N54: Australia | P54: Z_HISTORICAL_Y_Non Operational Control | Q54: Z_HISTORICAL_Y_Non Operational Control | R54: Social Infra | S54: Downer | T54: 100.0000 | W54: Classification | X54: -37.857 | Y54: 144.789 | Z54: 239 | AB54: 2018/06/30
A55: Downer | B55: _CLOSED_Anglo TXL | C55: Site | D55: L9.J.37240023 | E55: 37240023 | M55: Moranbah | N55: Australia | P55: Operational Control | Q55: Operational Control | R55: Energy and Utilities (EU) | S55: Downer | T55: 100.0000 | W55: Classification | Z55: 310 | AA55: 2023/12/06 | AB55: 2024/10/12
A56: Downer | B56: _CLOSED_APA SA | C56: Depot | D56: L9.J.24170135 | E56: L9.J.24170135 | G56: Duplicate location of Gepps Cross. (Part of the SA Gas business office) | M56: South Australia | N56: Australia | P56: Operational Control | Q56: Operational Control | R56: Energy and Utilities (EU) | S56: Downer | T56: 100.0000 | W56: Classification | AB56: 2022/06/30
A57: Downer | B57: _CLOSED_Asphalt _Whangarei | C57: Other | D57: L9.DNZJ.3502 | E57: 5010 | G57: Production of materials for road construction - New facilities established for more granular reporting and to reflect new structure for FY17. See facility named "NZ-Products" for historical data. | H57: 116-118 Port Road | I57: Whangarei | J57: Northland | K57: 9016 | L57: New Zealand | M57: Whangarei | N57: New Zealand | P57: Operational Control | Q57: Operational Control | R57: Transport & Infrastructure (T&I) | S57: Downer | T57: 100.0000 | U57: 1899/12/31 | W57: Classification | X57: -35.7431694 | Y57: 174.3415903 | Z57: 310 | AA57: 2017/07/01
A58: Downer | B58: _CLOSED_Asphalt Prod - Mowbray (OLD) | C58: Asphalt Plant | D58: L9.J.170360 | E58: 182 | G58: previously used L9.J.17030565, which has now transferred to New Mowbray Asphalt Envizi location. Replaced with L9.J.170360 | H58: Remount Road | I58: Mowbray | J58: TAS | K58: 7248 | L58: Australia | M58: Tasmania | N58: Australia | P58: Asphalt Plants | Q58: Asphalt Plants | R58: Asphalt Plants | S58: Downer | T58: 100.0000 | W58: Portfolio | X58: -41.399 | Y58: 147.162 | Z58: 170
A59: Downer | B59: _CLOSED_Asphalt Prod - Mowbray (OLD) | C59: Asphalt Plant | D59: L9.J.170360 | E59: 182 | G59: previously used L9.J.17030565, which has now transferred to New Mowbray Asphalt Envizi location. Replaced with L9.J.170360 | H59: Remount Road | I59: Mowbray | J59: TAS | K59: 7248 | L59: Australia | M59: Tasmania | N59: Australia | P59: Operational Control | Q59: Operational Control | R59: Transport & Infrastructure (T&I) | S59: Downer | T59: 100.0000 | W59: Classification | X59: -41.399 | Y59: 147.162 | Z59: 170
A60: Downer | B60: _CLOSED_Asphalt Prod - Rosehill (OLD) | C60: Asphalt Plant | D60: L9.J.17010964 | E60: 248 | G60: Vacated this location at the end of June 2022 and shifted operations to Rosehill - Devon St. Please refer to attachments for further information. | H60: 1 Unwin Street | I60: Rosehill | J60: NSW | K60: 2142 | L60: Australia | M60: Lidcombe | N60: Australia | P60: Asphalt Plants | Q60: Asphalt Plants | R60: Asphalt Plants | S60: Downer | T60: 100.0000 | W60: Portfolio | X60: -33.828 | Y60: 151.023 | Z60: 170 | AB60: 2023/02/28
A61: Downer | B61: _CLOSED_Asphalt Prod - Rosehill (OLD) | C61: Asphalt Plant | D61: L9.J.17010964 | E61: 248 | G61: Vacated this location at the end of June 2022 and shifted operations to Rosehill - Devon St. Please refer to attachments for further information. | H61: 1 Unwin Street | I61: Rosehill | J61: NSW | K61: 2142 | L61: Australia | M61: Lidcombe | N61: Australia | P61: Operational Control | Q61: Operational Control | R61: Transport & Infrastructure (T&I) | S61: Downer | T61: 100.0000 | W61: Classification | X61: -33.828 | Y61: 151.023 | Z61: 170 | AB61: 2023/02/28
A62: Downer | B62: _CLOSED_Asphalt_Allied-JV | C62: Industrial | E62: 5295 | G62: Production of materials for road construction - New facilities established for more granular reporting and to reflect new structure for FY19 | M62: Tauranga | N62: New Zealand | P62: Z_HISTORICAL_Operational Control | Q62: Z_HISTORICAL_Operational Control | R62: Transport & Infrastructure | S62: Downer | T62: 100.0000 | W62: Classification | Z62: 310
A63: Downer | B63: _CLOSED_Asphalt_Auckland | C63: Other | D63: L9.DNZJ.3503 | E63: 5011 | G63: Production of materials for road construction - New facilities established for more granular reporting and to reflect new structure for FY17. See facility named "NZ-Products" for historical data. | H63: 645 Great South Rd, Penrose | I63: Auckland | J63: Auckland | K63: 3200 | L63: New Zealand | M63: Panmure | N63: New Zealand | P63: Operational Control | Q63: Operational Control | R63: Transport & Infrastructure (T&I) | S63: Downer | T63: 100.0000 | U63: 1899/12/31 | W63: Classification | X63: -36.9152136 | Y63: 174.820280899999 | Z63: 310 | AA63: 2017/07/01
A64: Downer | B64: _CLOSED_Asphalt_Dunedin | C64: Other | D64: L9.DNZJ.3508 | E64: 5012 | G64: Production of materials for road construction - New facilities established for more granular reporting and to reflect new structure for FY17. See facility named "NZ-Products" for historical data. | H64: 102 Parry Street | I64: Dunedin | J64: Otago | K64: 9810 | L64: New Zealand | M64: Dunedin | N64: New Zealand | P64: Operational Control | Q64: Operational Control | R64: Transport & Infrastructure (T&I) | S64: Downer | T64: 100.0000 | U64: 1899/12/31 | W64: Classification | X64: -45.8698393 | Y64: 170.5315648 | Z64: 310 | AA64: 2017/07/01
A65: Downer | B65: _CLOSED_Asphalt_Hamilton | C65: Other | D65: L9.DNZJ.3504 | E65: 5013 | G65: Production of materials for road construction - New facilities established for more granular reporting and to reflect new structure for FY17. See facility named "NZ-Products" for historical data. | H65: 16 Manchester Place, Te Rapa | I65: Hamilton | J65: Waikato | K65: 4312 | L65: New Zealand | M65: Hamilton | N65: New Zealand | P65: Operational Control | Q65: Operational Control | R65: Transport & Infrastructure (T&I) | S65: Downer | T65: 100.0000 | U65: 1899/12/31 | W65: Classification | X65: -37.754068 | Y65: 175.2370587 | Z65: 310 | AA65: 2017/07/01
A66: Downer | B66: _CLOSED_Asphalt_Invercargill | C66: Other | D66: L9.DNZJ.3509 | E66: 5014 | G66: Production of materials for road construction - New facilities established for more granular reporting and to reflect new structure for FY17. See facility named "NZ-Products" for historical data. | H66: 210 Mersey Street, Invercargill West | I66: Invercargill | J66: Southland | K66: 6035 | L66: New Zealand | M66: Invercargill | N66: New Zealand | P66: Operational Control | Q66: Operational Control | R66: Transport & Infrastructure (T&I) | S66: Downer | T66: 100.0000 | U66: 1899/12/31 | W66: Classification | X66: -46.4152187 | Y66: 168.3417097 | Z66: 310 | AA66: 2017/07/01
A67: Downer | B67: _CLOSED_Asphalt_Isacc-JV | C67: Industrial | D67: L9.DNZJ.3098 | E67: 5294 | G67: Production of materials for road construction - New facilities established for more granular reporting and to reflect new structure for FY19 | M67: Christchurch | N67: New Zealand | P67: Operational Control | Q67: Operational Control | R67: Transport & Infrastructure (T&I) | S67: Downer | T67: 100.0000 | U67: 1899/12/31 | W67: Classification | Z67: 310
A68: Downer | B68: _CLOSED_Asphalt_Mobile | C68: Asphalt Plant | D68: L9.DNZJ.3512 | E68: 5286 | G68: Mobile Asphalt plant relocated across NZ depending on contracts - assigned to head office as main location | M68: Auckland City | N68: New Zealand | P68: Asphalt Plants | Q68: Asphalt Plants | R68: Asphalt Plants | S68: Downer | T68: 100.0000 | W68: Portfolio
A69: Downer | B69: _CLOSED_Asphalt_Mobile | C69: Asphalt Plant | D69: L9.DNZJ.3512 | E69: 5286 | G69: Mobile Asphalt plant relocated across NZ depending on contracts - assigned to head office as main location | M69: Auckland City | N69: New Zealand | P69: Operational Control | Q69: Operational Control | R69: Transport & Infrastructure (T&I) | S69: Downer | T69: 100.0000 | U69: 1899/12/31 | W69: Classification
A70: Downer | B70: _CLOSED_Asphalt_New Plymouth | C70: Other | D70: L9.DNZJ.3505 | E70: 5015 | G70: Production of materials for road construction - New facilities established for more granular reporting and to reflect new structure for FY17. See facility named "NZ-Products" for historical data. | H70: 106 Rifle Range Rd, Waiwhakaiho | I70: New Plymouth | J70: Taranaki | K70: 9814 | L70: New Zealand | M70: New Plymouth | N70: New Zealand | P70: Operational Control | Q70: Operational Control | R70: Transport & Infrastructure (T&I) | S70: Downer | T70: 100.0000 | U70: 1899/12/31 | W70: Classification | X70: -39.042342 | Y70: 174.119168299999 | Z70: 310 | AA70: 2017/07/01
A71: Downer | B71: _CLOSED_Asphalt_Wellington | C71: Other | D71: L9.DNZJ.3507 | E71: 5016 | G71: Production of materials for road construction - New facilities established for more granular reporting and to reflect new structure for FY17. See facility named "NZ-Products" for historical data. | H71: Kiwi Point, 137 Centennial Highway, Ngauranga | I71: Wellington | J71: Wellington | K71: 8082 | L71: New Zealand | M71: Wellington | N71: New Zealand | P71: Operational Control | Q71: Operational Control | R71: Transport & Infrastructure (T&I) | S71: Downer | T71: 100.0000 | U71: 1899/12/31 | W71: Classification | X71: -41.237631 | Y71: 174.805085999999 | Z71: 310 | AA71: 2017/07/01
A72: Downer | B72: _CLOSED_AusNet Mornington BESS | C72: Site | D72: L9.J.24135002 | E72: 24135002 | M72: Victoria | N72: Australia | P72: Operational Control | Q72: Operational Control | R72: Energy and Utilities (EU) | S72: Downer | T72: 100.0000 | U72: 2024/05/01 | W72: Classification | AB72: 2025/08/05
A73: Downer | B73: _CLOSED_B2B - Seymour Whyte JV | C73: Other | D73: L9.J.18710001 | E73: L9.J.18710001 | F73: L9.J.18710001 | M73: New South Wales | N73: Australia | P73: Y_Non Operational Control | Q73: Y_Non Operational Control | R73: DT Infrastructure | S73: Downer | T73: 100.0000 | W73: Classification
A74: Downer | B74: _CLOSED_Bango Wind Farm | C74: Other | D74: L9.J.37750008 | E74: IP-37750008 | G74: Operational control. Changed from Ref No 7040 | M74: New South Wales | N74: Australia | P74: Operational Control | Q74: Operational Control | R74: Energy and Utilities (EU) | S74: Downer | T74: 100.0000 | W74: Classification
A75: Downer | B75: _closed_Barwon Water | C75: Depot | E75: 7042 | M75: Geelong | N75: Australia | P75: Y_Non Operational Control | Q75: Y_Non Operational Control | R75: Energy and Utilities (EU) | S75: Downer | T75: 100.0000 | W75: Classification
A76: Downer | B76: _CLOSED_Beryl Solar Farm Construction Project | C76: Other | D76: L9.J.37110018 | E76: 7037 | H76: 39 Dehli Road | I76: North Ryde | J76: NSW | K76: 2113 | L76: Australia | M76: Gulgong | N76: Australia | P76: Operational Control | Q76: Operational Control | R76: Energy and Utilities (EU) | S76: Downer | T76: 100.0000 | W76: Classification | X76: -33.799820 | Y76: 151.143234 | Z76: 310
A77: Downer | B77: _CLOSED_BHP - Nickel West (NiW) | C77: Other | D77: L9.J.38280123 | E77: 38280123 | M77: North Ryde | N77: Australia | P77: Operational Control | Q77: Operational Control | R77: Energy and Utilities (EU) | S77: Downer | T77: 100.0000 | W77: Classification | AB77: 2026/07/22
A78: Downer | B78: _CLOSED_BHP Maintenance Services | C78: Other | D78: L9.J.38280046 | E78: 38280046 | M78: North Ryde | N78: Australia | P78: Operational Control | Q78: Operational Control | R78: Energy and Utilities (EU) | S78: Downer | T78: 100.0000 | W78: Classification | AB78: 2026/07/22
A79: Downer | B79: _CLOSED_BHP Yarnima TLine SP1 & SP2 | C79: Other | D79: L9.J.2413009501 | E79: 2413009501 | M79: North Ryde | N79: Australia | P79: Operational Control | Q79: Operational Control | R79: Energy and Utilities (EU) | S79: Downer | T79: 100.0000 | W79: Classification | AB79: 2026/07/22
A80: Downer | B80: _CLOSED_Bitumen_Bluff | C80: Other | D80: L9.DNZJ.3042 | E80: 5017 | G80: Storage and sale of Bitumen, Production and sale of Cutback Bitumen, Polymer Modified Bitumen and Bitumen Emulsions - New facilities established for more granular reporting and to reflect new structure for FY17. See facility named "NZ-Products" for historical data. | H80: 50 Foreshore Rd | I80: Bluff | J80: Southland | K80: 3116 | L80: New Zealand | M80: Bluff | N80: New Zealand | P80: Bitumen Plants | Q80: Bitumen Plants | R80: Bitumen Plants | S80: Downer | T80: 100.0000 | W80: Portfolio | X80: -46.5979746999999 | Y80: 168.342539 | Z80: 170 | AA80: 2017/07/01
A81: Downer | B81: _CLOSED_Bitumen_Bluff | C81: Other | D81: L9.DNZJ.3042 | E81: 5017 | G81: Storage and sale of Bitumen, Production and sale of Cutback Bitumen, Polymer Modified Bitumen and Bitumen Emulsions - New facilities established for more granular reporting and to reflect new structure for FY17. See facility named "NZ-Products" for historical data. | H81: 50 Foreshore Rd | I81: Bluff | J81: Southland | K81: 3116 | L81: New Zealand | M81: Bluff | N81: New Zealand | P81: Operational Control | Q81: Operational Control | R81: Transport & Infrastructure (T&I) | S81: Downer | T81: 100.0000 | U81: 1899/12/31 | W81: Classification | X81: -46.5979746999999 | Y81: 168.342539 | Z81: 170 | AA81: 2017/07/01
A82: Downer | B82: _CLOSED_Bitumen_Emulco-JV | C82: Industrial | D82: L9.DNZJ.3099 | E82: 5296 | G82: Production of materials for road construction - New facilities established for more granular reporting and to reflect new structure for FY19 | M82: Rotorua | N82: New Zealand | P82: Bitumen Plants | Q82: Bitumen Plants | R82: Bitumen Plants | S82: Downer | T82: 100.0000 | W82: Portfolio | Z82: 310
A83: Downer | B83: _CLOSED_Bitumen_Emulco-JV | C83: Industrial | D83: L9.DNZJ.3099 | E83: 5296 | G83: Production of materials for road construction - New facilities established for more granular reporting and to reflect new structure for FY19 | M83: Rotorua | N83: New Zealand | P83: Operational Control | Q83: Operational Control | R83: Transport & Infrastructure (T&I) | S83: Downer | T83: 100.0000 | U83: 1899/12/31 | W83: Classification | Z83: 310
A84: Downer | B84: _CLOSED_Bitumen_Lyttelton | C84: Other | D84: L9.DNZJ.3041 | E84: 5018 | G84: Storage and sale of Bitumen, Production and sale of Cutback Bitumen, Polymer Modified Bitumen and Bitumen Emulsions - New facilities established for more granular reporting and to reflect new structure for FY17. See facility named "NZ-Products" for historical data. | H84: Lyttelton Bitumen Terminal Charlotte Jane Quay, Port Lyttelton | I84: Lyttelton | J84: Canterbury | K84: 4340 | L84: New Zealand | M84: Christchurch | N84: New Zealand | P84: Bitumen Plants | Q84: Bitumen Plants | R84: Bitumen Plants | S84: Downer | T84: 100.0000 | W84: Portfolio | X84: -43.6105611 | Y84: 172.7041904 | Z84: 170 | AA84: 2017/07/01
A85: Downer | B85: _CLOSED_Bitumen_Lyttelton | C85: Other | D85: L9.DNZJ.3041 | E85: 5018 | G85: Storage and sale of Bitumen, Production and sale of Cutback Bitumen, Polymer Modified Bitumen and Bitumen Emulsions - New facilities established for more granular reporting and to reflect new structure for FY17. See facility named "NZ-Products" for historical data. | H85: Lyttelton Bitumen Terminal Charlotte Jane Quay, Port Lyttelton | I85: Lyttelton | J85: Canterbury | K85: 4340 | L85: New Zealand | M85: Christchurch | N85: New Zealand | P85: Operational Control | Q85: Operational Control | R85: Transport & Infrastructure (T&I) | S85: Downer | T85: 100.0000 | U85: 1899/12/31 | W85: Classification | X85: -43.6105611 | Y85: 172.7041904 | Z85: 170 | AA85: 2017/07/01
A86: Downer | B86: _CLOSED_Bitumen_Mt Maunganui | C86: Other | D86: L9.DNZJ.3040 | E86: 5019 | G86: Storage and sale of Bitumen, Production and sale of Cutback Bitumen, Polymer Modified Bitumen and Bitumen Emulsions - New facilities established for more granular reporting and to reflect new structure for FY17. See facility named "NZ-Products" for historical data. | H86: 198 Totara Street, Mt Maunganui | I86: Tauranga | J86: Bay of Plenty | K86: 3116 | L86: New Zealand | M86: Tauranga | N86: New Zealand | P86: Bitumen Plants | Q86: Bitumen Plants | R86: Bitumen Plants | S86: Downer | T86: 100.0000 | W86: Portfolio | X86: -37.6638657 | Y86: 176.186895 | Z86: 170 | AA86: 2017/07/01
A87: Downer | B87: _CLOSED_Bitumen_Mt Maunganui | C87: Other | D87: L9.DNZJ.3040 | E87: 5019 | G87: Storage and sale of Bitumen, Production and sale of Cutback Bitumen, Polymer Modified Bitumen and Bitumen Emulsions - New facilities established for more granular reporting and to reflect new structure for FY17. See facility named "NZ-Products" for historical data. | H87: 198 Totara Street, Mt Maunganui | I87: Tauranga | J87: Bay of Plenty | K87: 3116 | L87: New Zealand | M87: Tauranga | N87: New Zealand | P87: Operational Control | Q87: Operational Control | R87: Transport & Infrastructure (T&I) | S87: Downer | T87: 100.0000 | U87: 1899/12/31 | W87: Classification | X87: -37.6638657 | Y87: 176.186895 | Z87: 170 | AA87: 2017/07/01
A88: Downer | B88: _CLOSED_Bitumen_Taranaki | C88: Other | D88: L9.DNZJ.3045 | E88: 5020 | G88: Storage and sale of Bitumen, Production and sale of Cutback Bitumen, Polymer Modified Bitumen and Bitumen Emulsions - New facilities established for more granular reporting and to reflect new structure for FY17. See facility named "NZ-Products" for historical data. | H88: 1 Wharf Street, Port Taranaki | I88: New Plymouth | J88: Taranaki | K88: 9230 | L88: New Zealand | M88: New Plymouth | N88: New Zealand | P88: Bitumen Plants | Q88: Bitumen Plants | R88: Bitumen Plants | S88: Downer | T88: 100.0000 | W88: Portfolio | X88: -39.0577994 | Y88: 174.031262999999 | Z88: 170 | AA88: 2017/07/01
A89: Downer | B89: _CLOSED_Bitumen_Taranaki | C89: Other | D89: L9.DNZJ.3045 | E89: 5020 | G89: Storage and sale of Bitumen, Production and sale of Cutback Bitumen, Polymer Modified Bitumen and Bitumen Emulsions - New facilities established for more granular reporting and to reflect new structure for FY17. See facility named "NZ-Products" for historical data. | H89: 1 Wharf Street, Port Taranaki | I89: New Plymouth | J89: Taranaki | K89: 9230 | L89: New Zealand | M89: New Plymouth | N89: New Zealand | P89: Operational Control | Q89: Operational Control | R89: Transport & Infrastructure (T&I) | S89: Downer | T89: 100.0000 | U89: 1899/12/31 | W89: Classification | X89: -39.0577994 | Y89: 174.031262999999 | Z89: 170 | AA89: 2017/07/01
A90: Downer | B90: _CLOSED_Bitumen_Transport | C90: Other | D90: L9.DNZJ.3010 | E90: 5021 | G90: Transport of Bitumen to customers - New facilities established for more granular reporting and to reflect new structure for FY17. See facility named "NZ-Products" for historical data. | H90: 9 Owens Place, Mt Maunganui | I90: Tauranga | J90: Bay of Plenty | K90: 7201 | L90: New Zealand | M90: Tauranga | N90: New Zealand | P90: Bitumen Plants | Q90: Bitumen Plants | R90: Bitumen Plants | S90: Downer | T90: 100.0000 | W90: Portfolio | X90: -37.6782938 | Y90: 176.222364299999 | Z90: 461 | AA90: 2017/07/01
A91: Downer | B91: _CLOSED_Bitumen_Transport | C91: Other | D91: L9.DNZJ.3010 | E91: 5021 | G91: Transport of Bitumen to customers - New facilities established for more granular reporting and to reflect new structure for FY17. See facility named "NZ-Products" for historical data. | H91: 9 Owens Place, Mt Maunganui | I91: Tauranga | J91: Bay of Plenty | K91: 7201 | L91: New Zealand | M91: Tauranga | N91: New Zealand | P91: Operational Control | Q91: Operational Control | R91: Transport & Infrastructure (T&I) | S91: Downer | T91: 100.0000 | U91: 1899/12/31 | W91: Classification | X91: -37.6782938 | Y91: 176.222364299999 | Z91: 461 | AA91: 2017/07/01
A92: Downer | B92: _CLOSED_BO_Auckland | C92: Other | E92: 7020 | M92: Auckland | N92: New Zealand | P92: Z_HISTORICAL_Y_Non Operational Control | Q92: Z_HISTORICAL_Y_Non Operational Control | R92: Energy and Utilities (EU) | S92: Downer | T92: 100.0000 | W92: Classification | AB92: 2017/06/30
A93: Downer | B93: _CLOSED_BO_Auckland - Pacific Rise | C93: Commercial Office Space | D93: L9.DUN.300765 | E93: 883 | H93: 7A Pacific Rise | I93: Mt Wellington | J93: Auckland | K93: 1060 | L93: New Zealand | M93: Auckland City | N93: New Zealand | P93: Z_HISTORICAL_Y_Non Operational Control | Q93: Z_HISTORICAL_Y_Non Operational Control | R93: Energy and Utilities (EU) | S93: Downer | T93: 100.0000 | W93: Classification | AB93: 2017/06/30
A94: Downer | B94: _CLOSED_BO_Beenleigh (LWA) | C94: Other | E94: 135 | H94: Levels 1, 3 & 5, 106 City Rd | I94: Beenleigh | J94: QLD | K94: 4207 | L94: Australia | M94: Queensland | N94: Australia | P94: Z_HISTORICAL_Operational Control | Q94: Z_HISTORICAL_Operational Control | R94: Energy and Utilities (EU) | S94: Downer | T94: 100.0000 | W94: Classification | X94: -27.715123 | Y94: 153.20235 | AB94: 2017/06/30
A95: Downer | B95: _CLOSED_BO_Beenleigh (LWA) | C95: Other | E95: 135 | H95: Levels 1, 3 & 5, 106 City Rd | I95: Beenleigh | J95: QLD | K95: 4207 | L95: Australia | M95: Queensland | N95: Australia | P95: Z_HISTORICAL_Operational Control > Utilities (copy | Q95: Z_HISTORICAL_Operational Control > Utilities (copy | R95: Z_HISTORICAL_Operational Control > Utilities (copy | S95: Downer | T95: 100.0000 | W95: Portfolio | X95: -27.715123 | Y95: 153.20235 | AB95: 2017/06/30
A96: Downer | B96: _CLOSED_BO_Beenleigh Shopfront (LWA) | C96: Other | E96: 138 | H96: Shop 108A, 58 Manila St | I96: Beenleigh | J96: QLD | K96: 4207 | L96: Australia | M96: Queensland | N96: Australia | P96: Y_Non Operational Control | Q96: Y_Non Operational Control | R96: Energy and Utilities (EU) | S96: Downer | T96: 100.0000 | W96: Classification | X96: -27.714681 | Y96: 153.199807 | AB96: 2017/06/30
A97: Downer | B97: _CLOSED_BO_Bega (Carp St) | C97: Other | D97: L9.J.17010532 | E97: 141 | H97: Shop 6, 185A Carp St | I97: Bega | J97: NSW | K97: 2550 | L97: AUSTRALIA | M97: New South Wales | N97: Australia | P97: Z_HISTORICAL_Y_Non Operational Control | Q97: Z_HISTORICAL_Y_Non Operational Control | R97: Social Infra | S97: Downer | T97: 100.0000 | W97: Classification | X97: -36.673642 | Y97: 149.842283 | AB97: 2017/06/30
A98: Downer | B98: _CLOSED_BO_Bega (Swan St) | C98: Other | D98: L9.J.17012661 | E98: 140 | H98: 1-3 Swan St | I98: Bega | J98: NSW | K98: 2550 | L98: Australia | M98: New South Wales | N98: Australia | P98: Z_HISTORICAL_Y_Non Operational Control | Q98: Z_HISTORICAL_Y_Non Operational Control | R98: Energy and Utilities (EU) | S98: Downer | T98: 100.0000 | W98: Classification | X98: -36.673505 | Y98: 149.837551 | AB98: 2017/06/30
A99: Downer | B99: _CLOSED_BO_Belmont (Perth) | C99: Other | E99: 151 | H99: Unit 4/93 Francisco St | I99: Belmont | J99: WA | K99: 6104 | L99: Australia | M99: Western Australia | N99: Australia | P99: Y_Non Operational Control | Q99: Y_Non Operational Control | R99: Energy and Utilities (EU) | S99: Downer | T99: 100.0000 | W99: Classification | X99: -31.956195 | Y99: 115.919988 | AB99: 2017/06/30
A100: Downer | B100: _CLOSED_BO_Kawerau | C100: Other | D100: L9.S.26018029 | E100: 893 | H100: 4a Manukorihi Drive | I100: Kawerau | K100: 3169 | L100: New Zealand | M100: Bay of Plenty | N100: New Zealand | P100: Z_HISTORICAL_Y_Non Operational Control | Q100: Z_HISTORICAL_Y_Non Operational Control | R100: Energy and Utilities (EU) | S100: Downer | T100: 100.0000 | W100: Classification | AB100: 2017/06/30
...

Sheet Monthly Totals Check
A1: FY27 JV Revenue Exclusion — Monthly Totals: JV revenue (negated) vs Account Setup
A2: Each Account Setup monthly total must equal minus the JV revenue for that month. Extends by one row per month as FY27 fills out.
A3: Month | B3: JV Revenue (negated) | C3: Account Setup Total | D3: Difference | E3: Row Count (Setup) | F3: Status
A4: Jul 26 | B4: =-SUM('FY27 JV Rev'!B2:B6) -> -7.2 | C4: =SUMIFS(Account_Setup_and_Data_Load!$T:$T,Account_Setup_and_Data_Load!$L:$L,"2026-07-01") -> -7.2 | D4: =ROUND(C4-B4,4) -> 0 | E4: =COUNTIF(Account_Setup_and_Data_Load!$L:$L,"2026-07-01") -> 5 | F4: =IF(ABS(D4)<=0.001,"OK","MISMATCH") -> OK
A5: FY27 | B5: =SUM(B4:B4) -> -7.2 | C5: =SUM(C4:C4) -> -7.2 | D5: =ROUND(C5-B5,4) -> 0 | E5: =SUM(E4:E4) -> 5 | F5: =IF(ABS(D5)<=0.001,"OK","MISMATCH") -> OK

Sheet Check - By JV by Month
A1: Line-item check: Account Setup upload + source JV revenue = 0 for every JV and every month
A3: Joint Venture | B3: Jul 26 | C3: Status
A4: Allied Asphalt | B4: =ROUND(SUMIFS(Account_Setup_and_Data_Load!$T:$T,Account_Setup_and_Data_Load!$L:$L,"2026-07-01",Account_Setup_and_Data_Load!$R:$R,$A4)+'FY27 JV Rev'!B2,4) -> 0 | C4: =IF(SUMPRODUCT(ABS(B4:B4))<=0.001,"OK","MISMATCH") -> OK
A5: BIA | B5: =ROUND(SUMIFS(Account_Setup_and_Data_Load!$T:$T,Account_Setup_and_Data_Load!$L:$L,"2026-07-01",Account_Setup_and_Data_Load!$R:$R,$A5)+'FY27 JV Rev'!B3,4) -> 0 | C5: =IF(SUMPRODUCT(ABS(B5:B5))<=0.001,"OK","MISMATCH") -> OK
A6: EDI Rail- Bombardier Transportation | B6: =ROUND(SUMIFS(Account_Setup_and_Data_Load!$T:$T,Account_Setup_and_Data_Load!$L:$L,"2026-07-01",Account_Setup_and_Data_Load!$R:$R,$A6)+'FY27 JV Rev'!B4,4) -> 0 | C6: =IF(SUMPRODUCT(ABS(B6:B6))<=0.001,"OK","MISMATCH") -> OK
A7: Emulco | B7: =ROUND(SUMIFS(Account_Setup_and_Data_Load!$T:$T,Account_Setup_and_Data_Load!$L:$L,"2026-07-01",Account_Setup_and_Data_Load!$R:$R,$A7)+'FY27 JV Rev'!B5,4) -> 0 | C7: =IF(SUMPRODUCT(ABS(B7:B7))<=0.001,"OK","MISMATCH") -> OK
A8: Isaac Asphalt | B8: =ROUND(SUMIFS(Account_Setup_and_Data_Load!$T:$T,Account_Setup_and_Data_Load!$L:$L,"2026-07-01",Account_Setup_and_Data_Load!$R:$R,$A8)+'FY27 JV Rev'!B6,4) -> 0 | C8: =IF(SUMPRODUCT(ABS(B8:B8))<=0.001,"OK","MISMATCH") -> OK
A10: Overall | C10: =IF(SUMPRODUCT(ABS(B4:B8))<=0.001,"ALL OK","MISMATCH") -> ALL OK
