Workbook

Sheet Setup_locations_Basic_Palantir
A1: Organization | B1: Location Type | C1: Location Name | D1: Location Link | E1: Country | F1: Region | G1: Region Label | H1: Weather Station | I1: Station Assignment Method | J1: Id | K1: Ref No | L1: Location Ref | M1: Location Notes | N1: Address Link | O1: Address Type | P1: Address | Q1: City | R1: State | S1: Post Code | T1: Country Region
A2: Downer | B2: Other | C2: Essential EMS North Coast | E2: Australia | F2: =_xlfn.XLOOKUP($E2,Sheet1!$E:$E,Sheet1!F:F) -> North Ryde | G2: =_xlfn.XLOOKUP($E2,Sheet1!$E:$E,Sheet1!G:G) -> North Ryde [New South Wales] | I2: =_xlfn.XLOOKUP($E2,Sheet1!$E:$E,Sheet1!I:I) -> Default station | K2: L9.S.16013626 | L2: 16013626
A3: Downer | B3: Other | C3: Plant Pool | E3: Australia | F3: =_xlfn.XLOOKUP($E3,Sheet1!$E:$E,Sheet1!F:F) -> North Ryde | G3: =_xlfn.XLOOKUP($E3,Sheet1!$E:$E,Sheet1!G:G) -> North Ryde [New South Wales] | I3: =_xlfn.XLOOKUP($E3,Sheet1!$E:$E,Sheet1!I:I) -> Default station | K3: L9.J.150220 | L3: 150220
A4: Downer | B4: Other | C4: SA Power Networks | E4: Australia | F4: =_xlfn.XLOOKUP($E4,Sheet1!$E:$E,Sheet1!F:F) -> North Ryde | G4: =_xlfn.XLOOKUP($E4,Sheet1!$E:$E,Sheet1!G:G) -> North Ryde [New South Wales] | I4: =_xlfn.XLOOKUP($E4,Sheet1!$E:$E,Sheet1!I:I) -> Default station | K4: L9.S.16016295 | L4: 16016295
A5: Downer | B5: Other | C5: Western Power Meter Reading Service | E5: Australia | F5: =_xlfn.XLOOKUP($E5,Sheet1!$E:$E,Sheet1!F:F) -> North Ryde | G5: =_xlfn.XLOOKUP($E5,Sheet1!$E:$E,Sheet1!G:G) -> North Ryde [New South Wales] | I5: =_xlfn.XLOOKUP($E5,Sheet1!$E:$E,Sheet1!I:I) -> Default station | K5: L9.S.16016729 | L5: 16016729
A6: Downer | B6: Other | C6: Spotless Australia Overhead | E6: Australia | F6: =_xlfn.XLOOKUP($E6,Sheet1!$E:$E,Sheet1!F:F) -> North Ryde | G6: =_xlfn.XLOOKUP($E6,Sheet1!$E:$E,Sheet1!G:G) -> North Ryde [New South Wales] | I6: =_xlfn.XLOOKUP($E6,Sheet1!$E:$E,Sheet1!I:I) -> Default station | K6: L9.J.302001 | L6: 302001
A7: Downer | B7: Other | C7: Jemena Asset JGN - Gas Mtring Serv | E7: Australia | F7: =_xlfn.XLOOKUP($E7,Sheet1!$E:$E,Sheet1!F:F) -> North Ryde | G7: =_xlfn.XLOOKUP($E7,Sheet1!$E:$E,Sheet1!G:G) -> North Ryde [New South Wales] | I7: =_xlfn.XLOOKUP($E7,Sheet1!$E:$E,Sheet1!I:I) -> Default station | K7: L9.S.16013399 | L7: 16013399
A8: Downer | B8: Other | C8: National Bitumen Trans | E8: Australia | F8: =_xlfn.XLOOKUP($E8,Sheet1!$E:$E,Sheet1!F:F) -> North Ryde | G8: =_xlfn.XLOOKUP($E8,Sheet1!$E:$E,Sheet1!G:G) -> North Ryde [New South Wales] | I8: =_xlfn.XLOOKUP($E8,Sheet1!$E:$E,Sheet1!I:I) -> Default station | K8: L9.J.170935 | L8: 170935
A9: Downer | B9: Other | C9: Citylink & WGT Inc Resp & Main | E9: Australia | F9: =_xlfn.XLOOKUP($E9,Sheet1!$E:$E,Sheet1!F:F) -> North Ryde | G9: =_xlfn.XLOOKUP($E9,Sheet1!$E:$E,Sheet1!G:G) -> North Ryde [New South Wales] | I9: =_xlfn.XLOOKUP($E9,Sheet1!$E:$E,Sheet1!I:I) -> Default station | K9: L9.J.170269 | L9: 170269
A10: Downer | B10: Other | C10: SA Metro Maintenance | E10: Australia | F10: =_xlfn.XLOOKUP($E10,Sheet1!$E:$E,Sheet1!F:F) -> North Ryde | G10: =_xlfn.XLOOKUP($E10,Sheet1!$E:$E,Sheet1!G:G) -> North Ryde [New South Wales] | I10: =_xlfn.XLOOKUP($E10,Sheet1!$E:$E,Sheet1!I:I) -> Default station | K10: L9.J.170267 | L10: 170267
A11: Downer | B11: Other | C11: Melbourne City Council Serv Del | E11: Australia | F11: =_xlfn.XLOOKUP($E11,Sheet1!$E:$E,Sheet1!F:F) -> North Ryde | G11: =_xlfn.XLOOKUP($E11,Sheet1!$E:$E,Sheet1!G:G) -> North Ryde [New South Wales] | I11: =_xlfn.XLOOKUP($E11,Sheet1!$E:$E,Sheet1!I:I) -> Default station | K11: L9.S.16011998 | L11: 16011998
A12: Downer | B12: Other | C12: NEMA Field O/H | E12: Australia | F12: =_xlfn.XLOOKUP($E12,Sheet1!$E:$E,Sheet1!F:F) -> North Ryde | G12: =_xlfn.XLOOKUP($E12,Sheet1!$E:$E,Sheet1!G:G) -> North Ryde [New South Wales] | I12: =_xlfn.XLOOKUP($E12,Sheet1!$E:$E,Sheet1!I:I) -> Default station | K12: L9.J.170811 | L12: 170811
A13: Downer | B13: Other | C13: Sydney Water P4s Clearing | E13: Australia | F13: =_xlfn.XLOOKUP($E13,Sheet1!$E:$E,Sheet1!F:F) -> North Ryde | G13: =_xlfn.XLOOKUP($E13,Sheet1!$E:$E,Sheet1!G:G) -> North Ryde [New South Wales] | I13: =_xlfn.XLOOKUP($E13,Sheet1!$E:$E,Sheet1!I:I) -> Default station | K13: L9.J.241604 | L13: 241604
... A813: Downer | B813: Other | C813: Darling Downs Overhead | E813: Australia | F813: =_xlfn.XLOOKUP($E813,Sheet1!$E:$E,Sheet1!F:F) -> North Ryde | G813: =_xlfn.XLOOKUP($E813,Sheet1!$E:$E,Sheet1!G:G) -> North Ryde [New South Wales] | I813: =_xlfn.XLOOKUP($E813,Sheet1!$E:$E,Sheet1!I:I) -> Default station | K813: L9.S.14000496 | L813: 14000496
A814: Downer | B814: Other | C814: Construction Staff South | E814: New Zealand | F814: =_xlfn.XLOOKUP($E814,Sheet1!$E:$E,Sheet1!F:F) -> Auckland | G814: =_xlfn.XLOOKUP($E814,Sheet1!$E:$E,Sheet1!G:G) -> Auckland [New Zealand] | H814: =_xlfn.XLOOKUP($E814,Sheet1!$E:$E,Sheet1!H:H) -> Auckland, Whenuapai Aws | I814: =_xlfn.XLOOKUP($E814,Sheet1!$E:$E,Sheet1!I:I) -> Manual over-ride | K814: L9.DNZJ.8104 | L814: 8104
A815: Downer | B815: Other | C815: Construction Staff North | E815: New Zealand | F815: =_xlfn.XLOOKUP($E815,Sheet1!$E:$E,Sheet1!F:F) -> Auckland | G815: =_xlfn.XLOOKUP($E815,Sheet1!$E:$E,Sheet1!G:G) -> Auckland [New Zealand] | H815: =_xlfn.XLOOKUP($E815,Sheet1!$E:$E,Sheet1!H:H) -> Auckland, Whenuapai Aws | I815: =_xlfn.XLOOKUP($E815,Sheet1!$E:$E,Sheet1!I:I) -> Manual over-ride | K815: L9.DNZJ.8840 | L815: 8840
A816: Downer | B816: Other | C816: Kainga Ora-MGMK (Manukau/Mangere) | E816: New Zealand | F816: =_xlfn.XLOOKUP($E816,Sheet1!$E:$E,Sheet1!F:F) -> Auckland | G816: =_xlfn.XLOOKUP($E816,Sheet1!$E:$E,Sheet1!G:G) -> Auckland [New Zealand] | H816: =_xlfn.XLOOKUP($E816,Sheet1!$E:$E,Sheet1!H:H) -> Auckland, Whenuapai Aws | I816: =_xlfn.XLOOKUP($E816,Sheet1!$E:$E,Sheet1!I:I) -> Manual over-ride | K816: L9.S.24000030 | L816: 24000030
A817: Downer | B817: Other | C817: Wellington - WM 251 | E817: New Zealand | F817: =_xlfn.XLOOKUP($E817,Sheet1!$E:$E,Sheet1!F:F) -> Auckland | G817: =_xlfn.XLOOKUP($E817,Sheet1!$E:$E,Sheet1!G:G) -> Auckland [New Zealand] | H817: =_xlfn.XLOOKUP($E817,Sheet1!$E:$E,Sheet1!H:H) -> Auckland, Whenuapai Aws | I817: =_xlfn.XLOOKUP($E817,Sheet1!$E:$E,Sheet1!I:I) -> Manual over-ride | K817: L9.DUN.60251 | L817: 60251
A818: Downer | B818: Other | C818: GR Services Pre Connect | E818: New Zealand | F818: =_xlfn.XLOOKUP($E818,Sheet1!$E:$E,Sheet1!F:F) -> Auckland | G818: =_xlfn.XLOOKUP($E818,Sheet1!$E:$E,Sheet1!G:G) -> Auckland [New Zealand] | H818: =_xlfn.XLOOKUP($E818,Sheet1!$E:$E,Sheet1!H:H) -> Auckland, Whenuapai Aws | I818: =_xlfn.XLOOKUP($E818,Sheet1!$E:$E,Sheet1!I:I) -> Manual over-ride | K818: L9.EMS.410.10232 | L818: 10232
A819: Downer | B819: Other | C819: NSpark Mobile Network National | E819: New Zealand | F819: =_xlfn.XLOOKUP($E819,Sheet1!$E:$E,Sheet1!F:F) -> Auckland | G819: =_xlfn.XLOOKUP($E819,Sheet1!$E:$E,Sheet1!G:G) -> Auckland [New Zealand] | H819: =_xlfn.XLOOKUP($E819,Sheet1!$E:$E,Sheet1!H:H) -> Auckland, Whenuapai Aws | I819: =_xlfn.XLOOKUP($E819,Sheet1!$E:$E,Sheet1!I:I) -> Manual over-ride | K819: L9.DNZJ.10220 | L819: 10220
A820: Downer | B820: Other | C820: Kainga Ora - WEL (Wellington) | E820: New Zealand | F820: =_xlfn.XLOOKUP($E820,Sheet1!$E:$E,Sheet1!F:F) -> Auckland | G820: =_xlfn.XLOOKUP($E820,Sheet1!$E:$E,Sheet1!G:G) -> Auckland [New Zealand] | H820: =_xlfn.XLOOKUP($E820,Sheet1!$E:$E,Sheet1!H:H) -> Auckland, Whenuapai Aws | I820: =_xlfn.XLOOKUP($E820,Sheet1!$E:$E,Sheet1!I:I) -> Manual over-ride | K820: L9.S.24000031 | L820: 24000031
A821: Downer | B821: Other | C821: Waiouru Grounds Serv Del | E821: New Zealand | F821: =_xlfn.XLOOKUP($E821,Sheet1!$E:$E,Sheet1!F:F) -> Auckland | G821: =_xlfn.XLOOKUP($E821,Sheet1!$E:$E,Sheet1!G:G) -> Auckland [New Zealand] | H821: =_xlfn.XLOOKUP($E821,Sheet1!$E:$E,Sheet1!H:H) -> Auckland, Whenuapai Aws | I821: =_xlfn.XLOOKUP($E821,Sheet1!$E:$E,Sheet1!I:I) -> Manual over-ride | K821: L9.S.26016639 | L821: 26016639
A822: Downer | B822: Other | C822: Projects Corrections & JusticeDEL | E822: New Zealand | F822: =_xlfn.XLOOKUP($E822,Sheet1!$E:$E,Sheet1!F:F) -> Auckland | G822: =_xlfn.XLOOKUP($E822,Sheet1!$E:$E,Sheet1!G:G) -> Auckland [New Zealand] | H822: =_xlfn.XLOOKUP($E822,Sheet1!$E:$E,Sheet1!H:H) -> Auckland, Whenuapai Aws | I822: =_xlfn.XLOOKUP($E822,Sheet1!$E:$E,Sheet1!I:I) -> Manual over-ride | K822: L9.DNZJ.10139 | L822: 10139
A823: Downer | B823: Other | C823: Adelaide - Normanton to Geor | E823: New Zealand | F823: =_xlfn.XLOOKUP($E823,Sheet1!$E:$E,Sheet1!F:F) -> Auckland | G823: =_xlfn.XLOOKUP($E823,Sheet1!$E:$E,Sheet1!G:G) -> Auckland [New Zealand] | H823: =_xlfn.XLOOKUP($E823,Sheet1!$E:$E,Sheet1!H:H) -> Auckland, Whenuapai Aws | I823: =_xlfn.XLOOKUP($E823,Sheet1!$E:$E,Sheet1!I:I) -> Manual over-ride | K823: L9.EMS.410.10205 | L823: 10205
A824: Downer | B824: Other | C824: Manuwatu Overhead | E824: New Zealand | F824: =_xlfn.XLOOKUP($E824,Sheet1!$E:$E,Sheet1!F:F) -> Auckland | G824: =_xlfn.XLOOKUP($E824,Sheet1!$E:$E,Sheet1!G:G) -> Auckland [New Zealand] | H824: =_xlfn.XLOOKUP($E824,Sheet1!$E:$E,Sheet1!H:H) -> Auckland, Whenuapai Aws | I824: =_xlfn.XLOOKUP($E824,Sheet1!$E:$E,Sheet1!I:I) -> Manual over-ride | K824: L9.DNZJ.54936 | L824: 54936
A825: Downer | B825: Other | C825: Milling | E825: New Zealand | F825: =_xlfn.XLOOKUP($E825,Sheet1!$E:$E,Sheet1!F:F) -> Auckland | G825: =_xlfn.XLOOKUP($E825,Sheet1!$E:$E,Sheet1!G:G) -> Auckland [New Zealand] | H825: =_xlfn.XLOOKUP($E825,Sheet1!$E:$E,Sheet1!H:H) -> Auckland, Whenuapai Aws | I825: =_xlfn.XLOOKUP($E825,Sheet1!$E:$E,Sheet1!I:I) -> Manual over-ride | K825: L9.DNZJ.55163 | L825: 55163
... A947: Downer | B947: Other | C947: Hawkes Bay (TF1) | E947: New Zealand | F947: =_xlfn.XLOOKUP($E947,Sheet1!$E:$E,Sheet1!F:F) -> Auckland | G947: =_xlfn.XLOOKUP($E947,Sheet1!$E:$E,Sheet1!G:G) -> Auckland [New Zealand] | H947: =_xlfn.XLOOKUP($E947,Sheet1!$E:$E,Sheet1!H:H) -> Auckland, Whenuapai Aws | I947: =_xlfn.XLOOKUP($E947,Sheet1!$E:$E,Sheet1!I:I) -> Manual over-ride | K947: L9.DUN.80311 | L947: 80311

Sheet Sheet1
A1: Organization | B1: Location Type | C1: Location Name | D1: Location Link | E1: Country | F1: Region | G1: Region Label | H1: Weather Station | I1: Station Assignment Method | J1: Id | K1: Ref No | L1: Location Ref | M1: Location Notes | N1: Address Link | O1: Address Type | P1: Address | Q1: City | R1: State | S1: Post Code | T1: Country Region
A2: Downer | B2: Other | C2: _AI Testing | D2: 6046110 | E2: Australia | F2: North Ryde | G2: North Ryde [New South Wales] | I2: Default station
A3: Downer | B3: Hotel | C3: _CLOSED_Accommodation - NZ | D3: 6042214 | E3: New Zealand | F3: Auckland | G3: Auckland [New Zealand] | H3: Auckland, Whenuapai Aws | I3: Manual over-ride | K3: L9.WAU.000887 | L3: L9.WAU.000887
